Proyecto 2/src/design/Control.sv
module Control (
    input logic [6:0] opcode,
    input logic [2:0] func3,    
    
    // Señales de control del datapath
    output logic RegWrite,      // Escribir en registro destino
    output logic ALUSrc,        // 0: Rs2, 1: Inmediato para ALU
    output logic MemRead,       // Leer de memoria
    output logic MemWrite,      // Escribir a memoria  
    output logic MemtoReg,      // 0: ALU result, 1: Mem data a registro
    output logic Branch,        // Instrucción de branch
    output logic Jump,          // Instrucción de jump
    output logic [1:0] ALUOp,   // Tipo de operación para ALUControl
    output logic one_byte,      // Para sb, lb, lbu
    output logic two_byte,      // Para sh, lh, lhu
    output logic four_bytes,    // Para sw, lw
    output logic unsigned_load  // Para lbu, lhu
);

    always_comb begin
        // Valores por defecto (evita latches)
        RegWrite = 1'b0;
        ALUSrc = 1'b0;
        MemRead = 1'b0;
        MemWrite = 1'b0;
        MemtoReg = 1'b0;
        Branch = 1'b0;
        Jump = 1'b0;
        ALUOp = 2'b00;
        one_byte = 1'b0;
        two_byte = 1'b0;
        four_bytes = 1'b0;
        unsigned_load = 1'b0;
        
        case (opcode)
            // R-type: ADD, SUB, AND, OR, XOR, SLL, SRL, SRA, SLT, SLTU
            7'b0110011: begin
                RegWrite = 1'b1;    // Escribir resultado en Rd
                ALUSrc = 1'b0;      // Usar Rs2 (no inmediato)
                MemtoReg = 1'b0;    // Resultado de ALU a registro
                ALUOp = 2'b10;      // R-type: usar func3/func7
            end
            
            // I-type Load: LW, LH, LB, LHU, LBU
            7'b0000011: begin
                RegWrite = 1'b1;    // Escribir dato leído en Rd
                ALUSrc = 1'b1;      // Usar inmediato para dirección
                MemRead = 1'b1;     // Leer de memoria
                MemtoReg = 1'b1;    // Dato de memoria a registro
                ALUOp = 2'b00;      // Suma simple para dirección
                
                // Decodificar tipo de load según func3
                case (func3)
                    3'b000: begin   // LB - Load Byte
                        one_byte = 1'b1;
                        unsigned_load = 1'b0;  // Con signo
                    end
                    3'b001: begin   // LH - Load Halfword
                        two_byte = 1'b1;
                        unsigned_load = 1'b0;  // Con signo
                    end
                    3'b010: begin   // LW - Load Word
                        four_bytes = 1'b1;
                    end
                    3'b100: begin   // LBU - Load Byte Unsigned
                        one_byte = 1'b1;
                        unsigned_load = 1'b1;  // Sin signo
                    end
                    3'b101: begin   // LHU - Load Halfword Unsigned
                        two_byte = 1'b1;
                        unsigned_load = 1'b1;  // Sin signo
                    end
                    default: begin
                        // Caso por defecto - LW
                        four_bytes = 1'b1;
                    end
                endcase
            end
            
            // I-type Immediate: ADDI, SLTI, SLTIU, XORI, ORI, ANDI, SLLI, SRLI, SRAI
            7'b0010011: begin
                RegWrite = 1'b1;    // Escribir resultado en Rd
                ALUSrc = 1'b1;      // Usar inmediato
                MemtoReg = 1'b0;    // Resultado de ALU a registro
                ALUOp = 2'b11;      // I-type: usar func3 (similar a R-type)
            end
            
            // S-type Store: SW, SH, SB
            7'b0100011: begin
                ALUSrc = 1'b1;      // Usar inmediato para dirección
                MemWrite = 1'b1;    // Escribir a memoria
                ALUOp = 2'b00;      // Suma simple para dirección
                
                // Decodificar tipo de store según func3
                case (func3)
                    3'b000: begin   // SB - Store Byte
                        one_byte = 1'b1;
                    end
                    3'b001: begin   // SH - Store Halfword
                        two_byte = 1'b1;
                    end
                    3'b010: begin   // SW - Store Word
                        four_bytes = 1'b1;
                    end
                    default: begin
                        // Caso por defecto - SW
                        four_bytes = 1'b1;
                    end
                endcase
            end
            
            // B-type Branch: BEQ, BNE, BLT, BGE, BLTU, BGEU
            7'b1100011: begin
                ALUSrc = 1'b0;      // Comparar Rs1 con Rs2
                Branch = 1'b1;      // Es branch
                ALUOp = 2'b01;      // Branch: usar func3 para comparación
            end
            
            // U-type: LUI - Load Upper Immediate
            7'b0110111: begin
                RegWrite = 1'b1;    // Escribir inmediato en Rd
                ALUSrc = 1'b1;      // Usar inmediato
                MemtoReg = 1'b0;    // Resultado de ALU a registro
                ALUOp = 2'b00;      // Pasar inmediato directamente
            end
            
            // U-type: AUIPC - Add Upper Immediate to PC
            7'b0010111: begin
                RegWrite = 1'b1;    // Escribir PC+inmediato en Rd
                ALUSrc = 1'b1;      // Usar inmediato
                MemtoReg = 1'b0;    // Resultado de ALU a registro
                ALUOp = 2'b00;      // Suma PC + inmediato
            end
            
            // J-type: JAL - Jump and Link
            7'b1101111: begin
                RegWrite = 1'b1;    // Escribir PC+4 en Rd
                Jump = 1'b1;        // Es jump
                MemtoReg = 1'b0;    // PC+4 a registro
                ALUOp = 2'b00;      // No usar ALU para cálculo
            end
            
            // I-type: JALR - Jump and Link Register
            7'b1100111: begin
                RegWrite = 1'b1;    // Escribir PC+4 en Rd
                ALUSrc = 1'b1;      // Usar inmediato
                Jump = 1'b1;        // Es jump
                MemtoReg = 1'b0;    // PC+4 a registro
                ALUOp = 2'b00;      // Suma Rs1 + inmediato
            end
        endcase
    end
endmodule

Proyecto 3/src/sim/Control_tb.sv

`timescale 1ns/1ps

module Control_tb#(parameter WIDTH = 32);
    // Señales de entrada
    logic [6:0] opcode;
    logic [2:0] func3;
    
    // Señales de salida
    logic RegWrite;
    logic ALUSrc;
    logic MemRead;
    logic MemWrite;
    logic MemtoReg;
    logic Branch;
    logic Jump;
    logic [1:0] ALUOp;
    logic one_byte;
    logic two_byte;
    logic four_bytes;
    logic unsigned_load;
    
    // Instanciar el módulo bajo prueba
    Control uut (
        .opcode(opcode),
        .func3(func3),
        .RegWrite(RegWrite),
        .ALUSrc(ALUSrc),
        .MemRead(MemRead),
        .MemWrite(MemWrite),
        .MemtoReg(MemtoReg),
        .Branch(Branch),
        .Jump(Jump),
        .ALUOp(ALUOp),
        .one_byte(one_byte),
        .two_byte(two_byte),
        .four_bytes(four_bytes),
        .unsigned_load(unsigned_load)
    );
    
    // Variables para verificación
    int test_count = 0;
    int pass_count = 0;
    int fail_count = 0;
    
    // Task para verificar resultados
    task verify_signals(
        input string test_name,
        input logic exp_RegWrite,
        input logic exp_ALUSrc,
        input logic exp_MemRead,
        input logic exp_MemWrite,
        input logic exp_MemtoReg,
        input logic exp_Branch,
        input logic exp_Jump,
        input logic [1:0] exp_ALUOp,
        input logic exp_one_byte,
        input logic exp_two_byte,
        input logic exp_four_bytes,
        input logic exp_unsigned_load
    );
        test_count++;
        #1; // Pequeño delay para estabilización
        
        if (RegWrite === exp_RegWrite &&
            ALUSrc === exp_ALUSrc &&
            MemRead === exp_MemRead &&
            MemWrite === exp_MemWrite &&
            MemtoReg === exp_MemtoReg &&
            Branch === exp_Branch &&
            Jump === exp_Jump &&
            ALUOp === exp_ALUOp &&
            one_byte === exp_one_byte &&
            two_byte === exp_two_byte &&
            four_bytes === exp_four_bytes &&
            unsigned_load === exp_unsigned_load) begin
            $display("✓ PASS: %s", test_name);
            pass_count++;
        end else begin
            $display("✗ FAIL: %s", test_name);
            $display("  Expected: RegWrite=%b ALUSrc=%b MemRead=%b MemWrite=%b MemtoReg=%b Branch=%b Jump=%b ALUOp=%b one_byte=%b two_byte=%b four_bytes=%b unsigned_load=%b",
                     exp_RegWrite, exp_ALUSrc, exp_MemRead, exp_MemWrite, exp_MemtoReg, exp_Branch, exp_Jump, exp_ALUOp, exp_one_byte, exp_two_byte, exp_four_bytes, exp_unsigned_load);
            $display("  Actual:   RegWrite=%b ALUSrc=%b MemRead=%b MemWrite=%b MemtoReg=%b Branch=%b Jump=%b ALUOp=%b one_byte=%b two_byte=%b four_bytes=%b unsigned_load=%b",
                     RegWrite, ALUSrc, MemRead, MemWrite, MemtoReg, Branch, Jump, ALUOp, one_byte, two_byte, four_bytes, unsigned_load);
            fail_count++;
        end
    endtask
    
    initial begin
        $display("=== Iniciando testbench para módulo Control ===");
        $display("");
        
        // Test 1: R-type instructions (ADD, SUB, AND, OR, etc.)
        $display("--- Probando instrucciones R-type ---");
        opcode = 7'b0110011;
        func3 = 3'b000; // No importa para R-type en este módulo
        verify_signals("R-type (ADD/SUB)", 1'b1, 1'b0, 1'b0, 1'b0, 1'b0, 1'b0, 1'b0, 2'b10, 1'b0, 1'b0, 1'b0, 1'b0);
        
        // Test 2: I-type Load instructions
        $display("--- Probando instrucciones Load (I-type) ---");
        opcode = 7'b0000011;
        
        // LB - Load Byte
        func3 = 3'b000;
        verify_signals("LB (Load Byte)", 1'b1, 1'b1, 1'b1, 1'b0, 1'b1, 1'b0, 1'b0, 2'b00, 1'b1, 1'b0, 1'b0, 1'b0);
        
        // LH - Load Halfword
        func3 = 3'b001;
        verify_signals("LH (Load Halfword)", 1'b1, 1'b1, 1'b1, 1'b0, 1'b1, 1'b0, 1'b0, 2'b00, 1'b0, 1'b1, 1'b0, 1'b0);
        
        // LW - Load Word
        func3 = 3'b010;
        verify_signals("LW (Load Word)", 1'b1, 1'b1, 1'b1, 1'b0, 1'b1, 1'b0, 1'b0, 2'b00, 1'b0, 1'b0, 1'b1, 1'b0);
        
        // LBU - Load Byte Unsigned
        func3 = 3'b100;
        verify_signals("LBU (Load Byte Unsigned)", 1'b1, 1'b1, 1'b1, 1'b0, 1'b1, 1'b0, 1'b0, 2'b00, 1'b1, 1'b0, 1'b0, 1'b1);
        
        // LHU - Load Halfword Unsigned
        func3 = 3'b101;
        verify_signals("LHU (Load Halfword Unsigned)", 1'b1, 1'b1, 1'b1, 1'b0, 1'b1, 1'b0, 1'b0, 2'b00, 1'b0, 1'b1, 1'b0, 1'b1);
        
        // Test 3: I-type Immediate instructions
        $display("--- Probando instrucciones Immediate (I-type) ---");
        opcode = 7'b0010011;
        func3 = 3'b000; // ADDI como ejemplo
        verify_signals("ADDI (Add Immediate)", 1'b1, 1'b1, 1'b0, 1'b0, 1'b0, 1'b0, 1'b0, 2'b11, 1'b0, 1'b0, 1'b0, 1'b0);
        
        // Test 4: S-type Store instructions
        $display("--- Probando instrucciones Store (S-type) ---");
        opcode = 7'b0100011;
        
        // SB - Store Byte
        func3 = 3'b000;
        verify_signals("SB (Store Byte)", 1'b0, 1'b1, 1'b0, 1'b1, 1'b0, 1'b0, 1'b0, 2'b00, 1'b1, 1'b0, 1'b0, 1'b0);
        
        // SH - Store Halfword
        func3 = 3'b001;
        verify_signals("SH (Store Halfword)", 1'b0, 1'b1, 1'b0, 1'b1, 1'b0, 1'b0, 1'b0, 2'b00, 1'b0, 1'b1, 1'b0, 1'b0);
        
        // SW - Store Word
        func3 = 3'b010;
        verify_signals("SW (Store Word)", 1'b0, 1'b1, 1'b0, 1'b1, 1'b0, 1'b0, 1'b0, 2'b00, 1'b0, 1'b0, 1'b1, 1'b0);
        
        // Test 5: B-type Branch instructions
        $display("--- Probando instrucciones Branch (B-type) ---");
        opcode = 7'b1100011;
        func3 = 3'b000; // BEQ como ejemplo
        verify_signals("BEQ (Branch Equal)", 1'b0, 1'b0, 1'b0, 1'b0, 1'b0, 1'b1, 1'b0, 2'b01, 1'b0, 1'b0, 1'b0, 1'b0);
        
        // Test 6: U-type LUI
        $display("--- Probando instrucciones U-type ---");
        opcode = 7'b0110111;
        func3 = 3'b000; // No importa para LUI
        verify_signals("LUI (Load Upper Immediate)", 1'b1, 1'b1, 1'b0, 1'b0, 1'b0, 1'b0, 1'b0, 2'b00, 1'b0, 1'b0, 1'b0, 1'b0);
        
        // Test 7: U-type AUIPC
        opcode = 7'b0010111;
        func3 = 3'b000; // No importa para AUIPC
        verify_signals("AUIPC (Add Upper Immediate to PC)", 1'b1, 1'b1, 1'b0, 1'b0, 1'b0, 1'b0, 1'b0, 2'b00, 1'b0, 1'b0, 1'b0, 1'b0);
        
        // Test 8: J-type JAL
        $display("--- Probando instrucciones Jump ---");
        opcode = 7'b1101111;
        func3 = 3'b000; // No importa para JAL
        verify_signals("JAL (Jump and Link)", 1'b1, 1'b0, 1'b0, 1'b0, 1'b0, 1'b0, 1'b1, 2'b00, 1'b0, 1'b0, 1'b0, 1'b0);
        
        // Test 9: I-type JALR
        opcode = 7'b1100111;
        func3 = 3'b000; // JALR
        verify_signals("JALR (Jump and Link Register)", 1'b1, 1'b1, 1'b0, 1'b0, 1'b0, 1'b0, 1'b1, 2'b00, 1'b0, 1'b0, 1'b0, 1'b0);
        
        // Test 10: Opcode inválido (debe mantener valores por defecto)
        $display("--- Probando opcode inválido ---");
        opcode = 7'b1111111;
        func3 = 3'b000;
        verify_signals("Opcode inválido", 1'b0, 1'b0, 1'b0, 1'b0, 1'b0, 1'b0, 1'b0, 2'b00, 1'b0, 1'b0, 1'b0, 1'b0);
        
        // Test 11: func3 inválido para Load (debe usar default LW)
        $display("--- Probando func3 inválido en Load ---");
        opcode = 7'b0000011;
        func3 = 3'b111; // func3 inválido
        verify_signals("Load con func3 inválido (default LW)", 1'b1, 1'b1, 1'b1, 1'b0, 1'b1, 1'b0, 1'b0, 2'b00, 1'b0, 1'b0, 1'b1, 1'b0);
        
        // Test 12: func3 inválido para Store (debe usar default SW)
        $display("--- Probando func3 inválido en Store ---");
        opcode = 7'b0100011;
        func3 = 3'b111; // func3 inválido
        verify_signals("Store con func3 inválido (default SW)", 1'b0, 1'b1, 1'b0, 1'b1, 1'b0, 1'b0, 1'b0, 2'b00, 1'b0, 1'b0, 1'b1, 1'b0);
        
        // Mostrar resumen final
        $display("");
        $display("=== RESUMEN DE PRUEBAS ===");
        $display("Total de pruebas: %0d", test_count);
        $display("Pruebas exitosas: %0d", pass_count);
        $display("Pruebas fallidas: %0d", fail_count);
        
        if (fail_count == 0) begin
            $display(" ¡TODAS LAS PRUEBAS PASARON!");
        end else begin
            $display("  Algunas pruebas fallaron. Revisar implementación.");
        end
        
        $display("");
        $finish;
    end

    // Sistema de guardado de los resultados del testbench.
    initial begin
        $dumpfile("Control_tb.vcd");
        $dumpvars(0, Control_tb);
    end 

endmodule

Proyecto_2/src/build/Control_tb.vcd
$date
	Sun Jun 08 12:13:15 2025
$end
$version
	Icarus Verilog
$end
$timescale
	1ps
$end
$scope module Control_tb $end
$var wire 1 ! unsigned_load $end
$var wire 1 " two_byte $end
$var wire 1 # one_byte $end
$var wire 1 $ four_bytes $end
$var wire 1 % RegWrite $end
$var wire 1 & MemtoReg $end
$var wire 1 ' MemWrite $end
$var wire 1 ( MemRead $end
$var wire 1 ) Jump $end
$var wire 1 * Branch $end
$var wire 1 + ALUSrc $end
$var wire 2 , ALUOp [1:0] $end
$var parameter 32 - WIDTH $end
$var reg 3 . func3 [2:0] $end
$var reg 7 / opcode [6:0] $end
$var integer 32 0 fail_count [31:0] $end
$var integer 32 1 pass_count [31:0] $end
$var integer 32 2 test_count [31:0] $end
$scope module uut $end
$var wire 3 3 func3 [2:0] $end
$var wire 7 4 opcode [6:0] $end
$var reg 2 5 ALUOp [1:0] $end
$var reg 1 + ALUSrc $end
$var reg 1 * Branch $end
$var reg 1 ) Jump $end
$var reg 1 ( MemRead $end
$var reg 1 ' MemWrite $end
$var reg 1 & MemtoReg $end
$var reg 1 % RegWrite $end
$var reg 1 $ four_bytes $end
$var reg 1 # one_byte $end
$var reg 1 " two_byte $end
$var reg 1 ! unsigned_load $end
$upscope $end
$scope task verify_signals $end
$var reg 2 6 exp_ALUOp [1:0] $end
$var reg 1 7 exp_ALUSrc $end
$var reg 1 8 exp_Branch $end
$var reg 1 9 exp_Jump $end
$var reg 1 : exp_MemRead $end
$var reg 1 ; exp_MemWrite $end
$var reg 1 < exp_MemtoReg $end
$var reg 1 = exp_RegWrite $end
$var reg 1 > exp_four_bytes $end
$var reg 1 ? exp_one_byte $end
$var reg 1 @ exp_two_byte $end
$var reg 1 A exp_unsigned_load $end
$upscope $end
$upscope $end
$enddefinitions $end
$comment Show the parameter values. $end
$dumpall
b100000 -
$end
#0
$dumpvars
0A
0@
0?
0>
1=
0<
0;
0:
09
08
07
b10 6
b10 5
b110011 4
b0 3
b1 2
b0 1
b0 0
b110011 /
b0 .
b10 ,
0+
0*
0)
0(
0'
0&
1%
0$
0#
0"
0!
$end
#1000
1#
1&
1(
1+
b0 ,
b0 5
1%
b10 2
1?
b0 6
1<
1:
17
b11 /
b11 4
b1 1
#2000
1"
0#
1&
1(
1+
1%
b11 2
1@
0?
b1 .
b1 3
b10 1
#3000
1$
0"
1&
1(
1+
1%
b100 2
1>
0@
b10 .
b10 3
b11 1
#4000
1!
1#
0$
1&
1(
1+
1%
b101 2
1A
0>
1?
b100 .
b100 3
b100 1
#5000
1"
1!
0#
1&
1(
1+
1%
b110 2
1@
0?
b101 .
b101 3
b101 1
#6000
b11 ,
b11 5
0!
0"
0&
0(
1+
1%
b111 2
0A
0@
b11 6
0<
0:
b0 .
b0 3
b10011 /
b10011 4
b110 1
#7000
1#
1'
b0 ,
b0 5
1+
0%
b1000 2
1?
b0 6
1;
0=
b100011 /
b100011 4
b111 1
#8000
1"
0#
1'
1+
b1001 2
1@
0?
b1 .
b1 3
b1000 1
#9000
1$
0"
1'
1+
b1010 2
1>
0@
b10 .
b10 3
b1001 1
#10000
b1 ,
b1 5
1*
0$
0'
0+
b1011 2
0>
b1 6
18
0;
07
b0 .
b0 3
b1100011 /
b1100011 4
b1010 1
#11000
1+
1%
b0 ,
b0 5
0*
b1100 2
b0 6
08
17
1=
b110111 /
b110111 4
b1011 1
#12000
1+
1%
b1101 2
b10111 /
b10111 4
b1100 1
#13000
1)
0+
1%
b1110 2
19
07
b1101111 /
b1101111 4
b1101 1
#14000
1+
1)
1%
b1111 2
17
b1100111 /
b1100111 4
b1110 1
#15000
0)
0+
0%
b10000 2
09
07
0=
b1111111 /
b1111111 4
b1111 1
#16000
1$
1&
1(
1+
1%
b10001 2
1>
1<
1:
17
1=
b111 .
b111 3
b11 /
b11 4
b10000 1
#17000
1'
1$
0&
0(
1+
0%
b10010 2
0<
1;
0:
0=
b100011 /
b100011 4
b10001 1
#18000
b10010 1
