Proyecto 3/src/design/ALUcontrol.sv
module ALUControl (
    input logic [1:0] ALUOp,        // Del Control principal
    input logic [2:0] func3,        // De la instrucción
    input logic [6:0] func7,        // De la instrucción
    output logic [3:0] ALUCtrl      // Señal de control para ALU
);

    always_comb begin
        case (ALUOp)
            2'b00: begin // Load/Store/LUI/AUIPC/JAL/JALR
                ALUCtrl = 4'b0010; // ADD para direcciones / LUI pasa inmediato
            end
            
            2'b01: begin // Branch - comparaciones
                case (func3)
                    3'b000: ALUCtrl = 4'b1100; // BEQ - comparación igualdad
                    3'b001: ALUCtrl = 4'b1101; // BNE - comparación desigualdad
                    3'b100: ALUCtrl = 4'b1110; // BLT - menor que signed
                    3'b101: ALUCtrl = 4'b1111; // BGE - mayor igual signed
                    3'b110: ALUCtrl = 4'b0101; // BLTU - menor que unsigned
                    3'b111: ALUCtrl = 4'b0111; // BGEU - mayor igual unsigned
                    default: ALUCtrl = 4'b1100; // Default: BEQ
                endcase
            end
            
            2'b10: begin // R-type - operaciones registro-registro
                case (func3)
                    3'b000: begin // ADD/SUB
                        if (func7 == 7'b0100000)
                            ALUCtrl = 4'b0110; // SUB
                        else
                            ALUCtrl = 4'b0010; // ADD
                    end
                    3'b001: ALUCtrl = 4'b1000; // SLL
                    3'b010: ALUCtrl = 4'b0100; // SLT
                    3'b011: ALUCtrl = 4'b0011; // SLTU
                    3'b100: ALUCtrl = 4'b1001; // XOR
                    3'b101: begin // SRL/SRA
                        if (func7 == 7'b0100000)
                            ALUCtrl = 4'b1011; // SRA
                        else
                            ALUCtrl = 4'b1010; // SRL
                    end
                    3'b110: ALUCtrl = 4'b0001; // OR
                    3'b111: ALUCtrl = 4'b0000; // AND
                    default: ALUCtrl = 4'b0010; // Default: ADD
                endcase
            end
            
            2'b11: begin // I-type immediate - similar a R-type
                case (func3)
                    3'b000: ALUCtrl = 4'b0010; // ADDI
                    3'b001: ALUCtrl = 4'b1000; // SLLI
                    3'b010: ALUCtrl = 4'b0100; // SLTI
                    3'b011: ALUCtrl = 4'b0011; // SLTIU
                    3'b100: ALUCtrl = 4'b1001; // XORI
                    3'b101: begin // SRLI/SRAI
                        if (func7 == 7'b0100000)
                            ALUCtrl = 4'b1011; // SRAI
                        else
                            ALUCtrl = 4'b1010; // SRLI
                    end
                    3'b110: ALUCtrl = 4'b0001; // ORI
                    3'b111: ALUCtrl = 4'b0000; // ANDI
                    default: ALUCtrl = 4'b0010; // Default: ADD
                endcase
            end
            
            default: ALUCtrl = 4'b0010; // Default: ADD
        endcase
    end
endmodule

Proyecto_2/src/sim/ALUControl_tb.sv
`timescale 1ns / 1ps

module ALUControl_tb;

    // Señales de entrada
    logic [1:0] ALUOp;
    logic [2:0] func3;
    logic [6:0] func7;
    
    // Señal de salida
    logic [3:0] ALUCtrl;
    
    // Instanciar el módulo bajo prueba
    ALUControl uut (
        .ALUOp(ALUOp),
        .func3(func3),
        .func7(func7),
        .ALUCtrl(ALUCtrl)
    );
    
    // Variables para verificación
    int test_count = 0;
    int pass_count = 0;
    int fail_count = 0;
    
    // Task para verificar resultados
    task verify_alucontrol(
        input string test_name,
        input logic [3:0] expected_ctrl
    );
        test_count++;
        #1; // Pequeño delay para estabilización
        
        if (ALUCtrl === expected_ctrl) begin
            $display("✓ PASS: %s - ALUCtrl = %b", test_name, ALUCtrl);
            pass_count++;
        end else begin
            $display("✗ FAIL: %s", test_name);
            $display("  Expected: ALUCtrl = %b", expected_ctrl);
            $display("  Actual:   ALUCtrl = %b", ALUCtrl);
            fail_count++;
        end
    endtask
    
    initial begin
        $display("=== Iniciando testbench para módulo ALUControl ===");
        $display("");
        
        // Test ALUOp = 00 (Load/Store/LUI/AUIPC/JAL/JALR)
        $display("--- Probando ALUOp = 00 (Load/Store/Immediate Upper) ---");
        ALUOp = 2'b00;
        func3 = 3'b000; // No importa
        func7 = 7'b0000000; // No importa
        verify_alucontrol("Load/Store/LUI/AUIPC", 4'b0010); // ADD
        
        // Test ALUOp = 01 (Branch instructions)
        $display("--- Probando ALUOp = 01 (Branch comparisons) ---");
        ALUOp = 2'b01;
        
        func3 = 3'b000; // BEQ
        verify_alucontrol("BEQ", 4'b1100);
        
        func3 = 3'b001; // BNE
        verify_alucontrol("BNE", 4'b1101);
        
        func3 = 3'b100; // BLT
        verify_alucontrol("BLT", 4'b1110);
        
        func3 = 3'b101; // BGE
        verify_alucontrol("BGE", 4'b1111);
        
        func3 = 3'b110; // BLTU
        verify_alucontrol("BLTU", 4'b0101);
        
        func3 = 3'b111; // BGEU
        verify_alucontrol("BGEU", 4'b0111);
        
        func3 = 3'b010; // func3 inválido para branch
        verify_alucontrol("Branch inválido (default BEQ)", 4'b1100);
        
        // Test ALUOp = 10 (R-type instructions)
        $display("--- Probando ALUOp = 10 (R-type operations) ---");
        ALUOp = 2'b10;
        
        // ADD
        func3 = 3'b000;
        func7 = 7'b0000000;
        verify_alucontrol("ADD", 4'b0010);
        
        // SUB
        func3 = 3'b000;
        func7 = 7'b0100000;
        verify_alucontrol("SUB", 4'b0110);
        
        // SLL
        func3 = 3'b001;
        func7 = 7'b0000000; // No importa para SLL
        verify_alucontrol("SLL", 4'b1000);
        
        // SLT
        func3 = 3'b010;
        verify_alucontrol("SLT", 4'b0100);
        
        // SLTU
        func3 = 3'b011;
        verify_alucontrol("SLTU", 4'b0011);
        
        // XOR
        func3 = 3'b100;
        verify_alucontrol("XOR", 4'b1001);
        
        // SRL
        func3 = 3'b101;
        func7 = 7'b0000000;
        verify_alucontrol("SRL", 4'b1010);
        
        // SRA
        func3 = 3'b101;
        func7 = 7'b0100000;
        verify_alucontrol("SRA", 4'b1011);
        
        // OR
        func3 = 3'b110;
        verify_alucontrol("OR", 4'b0001);
        
        // AND
        func3 = 3'b111;
        verify_alucontrol("AND", 4'b0000);
        
        // Test ALUOp = 11 (I-type immediate instructions)
        $display("--- Probando ALUOp = 11 (I-type immediate) ---");
        ALUOp = 2'b11;
        
        // ADDI
        func3 = 3'b000;
        func7 = 7'b0000000; // No importa para ADDI
        verify_alucontrol("ADDI", 4'b0010);
        
        // SLLI
        func3 = 3'b001;
        verify_alucontrol("SLLI", 4'b1000);
        
        // SLTI
        func3 = 3'b010;
        verify_alucontrol("SLTI", 4'b0100);
        
        // SLTIU
        func3 = 3'b011;
        verify_alucontrol("SLTIU", 4'b0011);
        
        // XORI
        func3 = 3'b100;
        verify_alucontrol("XORI", 4'b1001);
        
        // SRLI
        func3 = 3'b101;
        func7 = 7'b0000000;
        verify_alucontrol("SRLI", 4'b1010);
        
        // SRAI
        func3 = 3'b101;
        func7 = 7'b0100000;
        verify_alucontrol("SRAI", 4'b1011);
        
        // ORI
        func3 = 3'b110;
        verify_alucontrol("ORI", 4'b0001);
        
        // ANDI
        func3 = 3'b111;
        verify_alucontrol("ANDI", 4'b0000);
        
        // Test casos edge
        $display("--- Probando casos edge ---");
        
        // ALUOp inválido
        ALUOp = 2'b00; // Reset a valor válido primero
        #1;
        ALUOp = 2'bxx; // Valor inválido
        func3 = 3'b000;
        func7 = 7'b0000000;
        verify_alucontrol("ALUOp inválido", 4'b0010); // Default ADD
        
        // func3 inválido para R-type
        ALUOp = 2'b10;
        func3 = 3'bxxx;
        verify_alucontrol("R-type func3 inválido", 4'b0010); // Default ADD
        
        // func3 inválido para I-type
        ALUOp = 2'b11;
        func3 = 3'bxxx;
        verify_alucontrol("I-type func3 inválido", 4'b0010); // Default ADD
        
        // Mostrar resumen final
        $display("");
        $display("=== RESUMEN DE PRUEBAS ALUControl ===");
        $display("Total de pruebas: %0d", test_count);
        $display("Pruebas exitosas: %0d", pass_count);
        $display("Pruebas fallidas: %0d", fail_count);
        
        if (fail_count == 0) begin
            $display(" ¡TODAS LAS PRUEBAS DE ALUControl PASARON!");
        end else begin
            $display("  Algunas pruebas de ALUControl fallaron.");
        end
        
        $display("");
        $finish;
    end
    // Sistema de guardado de los resultados del testbench.
    initial begin
        $dumpfile("ALUControl_tb.vcd");
        $dumpvars(0, ALUControl_tb);
    end 
endmodule

Proyecto_3/src/build/ALUControl_tb.vcd
$date
	Sun Jun 08 12:46:20 2025
$end
$version
	Icarus Verilog
$end
$timescale
	1ps
$end
$scope module ALUControl_tb $end
$var wire 4 ! ALUCtrl [3:0] $end
$var reg 2 " ALUOp [1:0] $end
$var reg 3 # func3 [2:0] $end
$var reg 7 $ func7 [6:0] $end
$var integer 32 % fail_count [31:0] $end
$var integer 32 & pass_count [31:0] $end
$var integer 32 ' test_count [31:0] $end
$scope module uut $end
$var wire 2 ( ALUOp [1:0] $end
$var wire 3 ) func3 [2:0] $end
$var wire 7 * func7 [6:0] $end
$var reg 4 + ALUCtrl [3:0] $end
$upscope $end
$scope task verify_alucontrol $end
$var reg 4 , expected_ctrl [3:0] $end
$upscope $end
$upscope $end
$enddefinitions $end
$comment Show the parameter values. $end
$dumpall
$end
#0
$dumpvars
b10 ,
b10 +
b0 *
b0 )
b0 (
b1 '
b0 &
b0 %
b0 $
b0 #
b0 "
b10 !
$end
#1000
b1100 !
b1100 +
b10 '
b1100 ,
b1 "
b1 (
b1 &
#2000
b1101 !
b1101 +
b11 '
b1101 ,
b1 #
b1 )
b10 &
#3000
b1110 !
b1110 +
b100 '
b1110 ,
b100 #
b100 )
b11 &
#4000
b1111 !
b1111 +
b101 '
b1111 ,
b101 #
b101 )
b100 &
#5000
b101 !
b101 +
b110 '
b101 ,
b110 #
b110 )
b101 &
#6000
b111 !
b111 +
b111 '
b111 ,
b111 #
b111 )
b110 &
#7000
b1100 !
b1100 +
b1000 '
b1100 ,
b10 #
b10 )
b111 &
#8000
b10 !
b10 +
b1001 '
b10 ,
b0 #
b0 )
b10 "
b10 (
b1000 &
#9000
b110 !
b110 +
b1010 '
b110 ,
b100000 $
b100000 *
b1001 &
#10000
b1000 !
b1000 +
b1011 '
b1000 ,
b0 $
b0 *
b1 #
b1 )
b1010 &
#11000
b100 !
b100 +
b1100 '
b100 ,
b10 #
b10 )
b1011 &
#12000
b11 !
b11 +
b1101 '
b11 ,
b11 #
b11 )
b1100 &
#13000
b1001 !
b1001 +
b1110 '
b1001 ,
b100 #
b100 )
b1101 &
#14000
b1010 !
b1010 +
b1111 '
b1010 ,
b101 #
b101 )
b1110 &
#15000
b1011 !
b1011 +
b10000 '
b1011 ,
b100000 $
b100000 *
b1111 &
#16000
b1 !
b1 +
b10001 '
b1 ,
b110 #
b110 )
b10000 &
#17000
b0 !
b0 +
b10010 '
b0 ,
b111 #
b111 )
b10001 &
#18000
b10 !
b10 +
b10011 '
b10 ,
b0 $
b0 *
b0 #
b0 )
b11 "
b11 (
b10010 &
#19000
b1000 !
b1000 +
b10100 '
b1000 ,
b1 #
b1 )
b10011 &
#20000
b100 !
b100 +
b10101 '
b100 ,
b10 #
b10 )
b10100 &
#21000
b11 !
b11 +
b10110 '
b11 ,
b11 #
b11 )
b10101 &
#22000
b1001 !
b1001 +
b10111 '
b1001 ,
b100 #
b100 )
b10110 &
#23000
b1010 !
b1010 +
b11000 '
b1010 ,
b101 #
b101 )
b10111 &
#24000
b1011 !
b1011 +
b11001 '
b1011 ,
b100000 $
b100000 *
b11000 &
#25000
b1 !
b1 +
b11010 '
b1 ,
b110 #
b110 )
b11001 &
#26000
b0 !
b0 +
b11011 '
b0 ,
b111 #
b111 )
b11010 &
#27000
b10 !
b10 +
b0 "
b0 (
b11011 &
#28000
b11100 '
b10 ,
b0 $
b0 *
b0 #
b0 )
bx "
bx (
#29000
b11101 '
bx #
bx )
b10 "
b10 (
b11100 &
#30000
b11110 '
b11 "
b11 (
b11101 &
#31000
b11110 &
