Proyecto 3/src/design/DataMemory.sv
// Módulo de memoria de datos mejorado para procesador RISC-V
// Soporta accesos de 1, 2 y 4 bytes con organización byte-addressable
// Optimizado específicamente para Yosys
module DataMemory #(parameter WIDTH=32, parameter DEPTH=12) ( // Reducido a 4KB para evitar problemas de síntesis
    // Señales de entrada y salida
    input logic clk, rst, 
    input logic MemWrite, MemRead,              // Señales de control para escribir y leer
    input logic [DEPTH-1:0] Address,            // Dirección de memoria (byte address)
    input logic [WIDTH-1:0] WriteData,          // Dato a escribir
    input logic one_byte,                       // Para sb, lb, lbu
    input logic two_byte,                       // Para sh, lh, lhu  
    input logic four_bytes,                     // Para sw, lw
    input logic unsigned_load,                  // Para lbu, lhu (extensión sin signo)
    output logic [WIDTH-1:0] ReadData           // Dato leído
);
    
    // Memoria de datos organizada por bytes
    logic [7:0] DataMem [2**DEPTH-1:0];
    
    // Señales intermedias para lectura -
    logic [7:0] mem_byte;
    logic [15:0] mem_halfword;
    logic [31:0] mem_word;
    
    // Señales de extensión 
    logic [31:0] byte_signed, byte_unsigned;
    logic [31:0] halfword_signed, halfword_unsigned;
    
    // Señales de control interno
    logic valid_address;
    logic valid_halfword_address;
    logic valid_word_address;
    
    // Validación de direcciones 
    assign valid_address = (Address < 2**DEPTH);
    assign valid_halfword_address = (Address + 1 < 2**DEPTH);
    assign valid_word_address = (Address + 3 < 2**DEPTH);
    
    // Lectura de memoria 
    assign mem_byte = DataMem[Address];
    assign mem_halfword = {DataMem[Address + 1], DataMem[Address]};
    assign mem_word = {DataMem[Address + 3], DataMem[Address + 2], 
                       DataMem[Address + 1], DataMem[Address]};
    
    // Extensiones de signo y cero 
    assign byte_signed = {{24{mem_byte[7]}}, mem_byte};
    assign byte_unsigned = {24'h000000, mem_byte};
    assign halfword_signed = {{16{mem_halfword[15]}}, mem_halfword};
    assign halfword_unsigned = {16'h0000, mem_halfword};

    int i;
    initial begin
    for (int i = 0; i < DEPTH; i++) begin
        DataMem[i] = 0; // Initialize memory to zero
    end
    
    end
    // Escritura síncrona - mantenida simple para Yosys
    always_ff @(posedge clk) begin
        if (!rst && MemWrite && valid_address) begin
            case ({four_bytes, two_byte, one_byte})
                3'b001: begin // sb - store byte
                    DataMem[Address] <= WriteData[7:0];
                end
                3'b010: begin // sh - store halfword
                    if (valid_halfword_address) begin
                        DataMem[Address]     <= WriteData[7:0];
                        DataMem[Address + 1] <= WriteData[15:8];
                    end
                end
                3'b100: begin // sw - store word
                    if (valid_word_address) begin
                        DataMem[Address]     <= WriteData[7:0];
                        DataMem[Address + 1] <= WriteData[15:8];
                        DataMem[Address + 2] <= WriteData[23:16];
                        DataMem[Address + 3] <= WriteData[31:24];
                    end
                end
                default: begin
                    // No operation - Yosys optimiza away este caso
                end
            endcase
        end
    end
    
    // Lectura combinacional 
    always_comb begin
        if (rst) begin
            ReadData = 32'h00000000;
        end
        else if (MemRead && valid_address) begin
            case ({four_bytes, two_byte, one_byte})
                3'b001: begin // lb/lbu - load byte
                    ReadData = unsigned_load ? byte_unsigned : byte_signed;
                end
                3'b010: begin // lh/lhu - load halfword
                    if (valid_halfword_address) begin
                        ReadData = unsigned_load ? halfword_unsigned : halfword_signed;
                    end else begin
                        ReadData = 32'h00000000;
                    end
                end
                3'b100: begin // lw - load word
                    if (valid_word_address) begin
                        ReadData = mem_word;
                    end else begin
                        ReadData = 32'h00000000;
                    end
                end
                default: begin
                    ReadData = 32'h00000000;
                end
            endcase
        end
        else begin
            ReadData = 32'h00000000;
        end
    end

endmodule

Proyecto_2/src/sim/DataMemory_tb.sv
module DataMemory_tb();
    
    //=================================================================
    // CONFIGURACIÓN DEL TESTBENCH
    //=================================================================
    
    // Parámetros del módulo de memoria
    parameter WIDTH = 32;        // Ancho de datos en bits (32 bits = 4 bytes)
    parameter DEPTH = 12;        // Bits de dirección (2^12 = 4096 direcciones)
    parameter CLK_PERIOD = 10;   // Período del reloj en unidades de tiempo
    
    //=================================================================
    // DECLARACIÓN DE SEÑALES
    //=================================================================
    
    // Señales de control del sistema
    logic clk;              // Reloj del sistema
    logic rst;              // Reset (reinicio del sistema)
    
    // Señales de control de memoria
    logic MemWrite;         // Habilita escritura en memoria (1 = escribir)
    logic MemRead;          // Habilita lectura de memoria (1 = leer)
    
    // Señales de selección de tamaño de datos
    logic one_byte;         // Selecciona operación de 1 byte
    logic two_byte;         // Selecciona operación de 2 bytes (halfword)
    logic four_bytes;       // Selecciona operación de 4 bytes (word completa)
    logic unsigned_load;    // 1 = carga sin signo, 0 = carga con signo
    
    // Señales de datos y direcciones
    logic [DEPTH-1:0] Address;    // Dirección de memoria (12 bits)
    logic [WIDTH-1:0] WriteData;  // Datos a escribir (32 bits)
    logic [WIDTH-1:0] ReadData;   // Datos leídos de memoria (32 bits)
    
    //=================================================================
    // INSTANCIACIÓN DEL MÓDULO BAJO PRUEBA (DUT)
    //=================================================================
    
    // Conecta todas las señales automáticamente usando .*
    DataMemory #(WIDTH, DEPTH) dut (.*);
    
    //=================================================================
    // GENERACIÓN DEL RELOJ
    //=================================================================
    
    // Inicializa el reloj en 0
    initial clk = 0;
    
    // Cambia el reloj cada medio período (genera onda cuadrada)
    always #(CLK_PERIOD/2) clk = ~clk;
    
    //=================================================================
    // TAREAS AUXILIARES PARA SIMPLIFICAR LAS PRUEBAS
    //=================================================================
    
    // TAREA DE RESET: Reinicia el sistema
    task reset(); 
    begin 
        $display("🔄 Ejecutando reset del sistema...");
        rst = 1;           // Activa reset
        @(posedge clk);    // Espera un ciclo de reloj
        rst = 0;           // Desactiva reset
        $display("✅ Reset completado");
    end 
    endtask
    
    // TAREA DE ESCRITURA: Escribe datos en memoria
    task write(input [DEPTH-1:0] addr,      // Dirección donde escribir
               input [WIDTH-1:0] data,      // Datos a escribir
               input [2:0] size);           // Tamaño: 1=byte, 2=halfword, 4=word
    begin
        @(posedge clk);  // Sincroniza con el reloj
        
        // Configura la operación de escritura
        Address = addr;
        WriteData = data;
        MemWrite = 1'b1;    // Habilita escritura
        MemRead = 1'b0;     // Deshabilita lectura
        
        // Selecciona el tamaño de datos según el parámetro 'size'
        case(size)
            1: {one_byte, two_byte, four_bytes, unsigned_load} = 4'b1000;  // 1 byte
            2: {one_byte, two_byte, four_bytes, unsigned_load} = 4'b0100;  // 2 bytes
            4: {one_byte, two_byte, four_bytes, unsigned_load} = 4'b0010;  // 4 bytes
            default: {one_byte, two_byte, four_bytes, unsigned_load} = 4'b0010;
        endcase
        
        @(posedge clk);     // Espera un ciclo para completar escritura
        MemWrite = 0;       // Deshabilita escritura
        
        $display("📝 Escribiendo: Addr=0x%03X, Data=0x%08X, Size=%0d bytes", 
                 addr, data, size);
    end 
    endtask
    
    // TAREA DE LECTURA: Lee datos de memoria
    task read(input [DEPTH-1:0] addr,       // Dirección a leer
              input [2:0] size,             // Tamaño: 1=byte, 2=halfword, 4=word
              input unsign = 0);            // 0=con signo, 1=sin signo
    begin
        @(posedge clk);  // Sincroniza con el reloj
        
        // Configura la operación de lectura
        Address = addr;
        MemWrite = 1'b0;    // Deshabilita escritura
        MemRead = 1'b1;     // Habilita lectura
        
        // Selecciona el tamaño y tipo de carga
        case(size)
            1: {one_byte, two_byte, four_bytes, unsigned_load} = {3'b100, unsign};
            2: {one_byte, two_byte, four_bytes, unsigned_load} = {3'b010, unsign};
            4: {one_byte, two_byte, four_bytes, unsigned_load} = 4'b0010;
            default: {one_byte, two_byte, four_bytes, unsigned_load} = 4'b0010;
        endcase
        
        @(posedge clk);     // Espera un ciclo para completar lectura
        
        $display(" Leyendo: Addr=0x%03X, Size=%0d bytes, %s → Data=0x%08X", 
                 addr, size, unsign ? "unsigned" : "signed", ReadData);
    end 
    endtask
    
    // TAREA DE VERIFICACIÓN: Compara el resultado con lo esperado
    task check(input [WIDTH-1:0] expected,  // Valor esperado
               input string test_name);     // Nombre de la prueba
    begin
        if (ReadData !== expected) begin
            $display(" FALLO en %s:", test_name);
            $display("   Esperado: 0x%08X", expected);
            $display("   Obtenido: 0x%08X", ReadData);
            $error("Test fallido: %s", test_name);
        end else begin
            $display(" ÉXITO en %s: 0x%08X", test_name, ReadData);
        end
    end 
    endtask
    
    //=================================================================
    // SECUENCIA PRINCIPAL DE PRUEBAS
    //=================================================================
    
    initial begin
        $display("\n" + "="*50);
        $display(" INICIANDO TESTBENCH DE MEMORIA DE DATOS");
        $display("="*50);
        
        // Inicialización del sistema
        reset();
        
        $display("\n PRUEBA 1: Escritura y lectura de palabras completas (32 bits)");
        write(0, 32'hDEADBEEF, 4);     // Escribe palabra completa en dirección 0
        read(0, 4);                     // Lee palabra completa
        check(32'hDEADBEEF, "Escritura/Lectura de palabra");
        
        $display("\nPRUEBA 2: Manejo de bytes con y sin signo");
        write(4, 32'h000000FF, 1);     // Escribe byte 0xFF (255 decimal)
        
        // Lee como byte con signo (0xFF se extiende a 0xFFFFFFFF = -1)
        read(4, 1, 0);                  
        check(32'hFFFFFFFF, "Byte con signo (extensión de signo)");
        
        // Lee como byte sin signo (0xFF se extiende a 0x000000FF = 255)
        read(4, 1, 1);                  
        check(32'h000000FF, "Byte sin signo (extensión con ceros)");
        
        $display("\n PRUEBA 3: Manejo de halfwords (16 bits) con y sin signo");
        write(8, 32'h0000FFFF, 2);     // Escribe halfword 0xFFFF
        
        // Lee como halfword con signo (0xFFFF = -1 en complemento a 2)
        read(8, 2, 0);                  
        check(32'hFFFFFFFF, "Halfword con signo");
        
        // Lee como halfword sin signo (0xFFFF = 65535 decimal)
        read(8, 2, 1);                  
        check(32'h0000FFFF, "Halfword sin signo");
        
        $display("\n PRUEBA 4: Verificación del formato little-endian");
        // En little-endian, el byte menos significativo se almacena primero
        write(12, 32'h12345678, 4);    // Escribe 0x12345678
        
        // En memoria se almacena como: [12][34][56][78] → [78][56][34][12]
        read(12, 1, 1);                // Lee primer byte (menos significativo)
        check(32'h00000078, "Little-endian: Byte 0 (LSB)");
        
        read(13, 1, 1);                // Lee segundo byte
        check(32'h00000056, "Little-endian: Byte 1");
        
        read(12, 2, 1);                // Lee halfword (2 bytes)
        check(32'h00005678, "Little-endian: Halfword");
        
        $display("\n PRUEBA 5: Pruebas en los límites de memoria");
        write(4092, 32'hAAAABBBB, 4); // Escribe cerca del final de memoria
        read(4092, 4);
        check(32'hAAAABBBB, "Escritura en límite de memoria");
        
        write(4095, 32'hCCCCDDDD, 1); // Escribe en la última dirección
        read(4095, 1, 1);
        check(32'h000000DD, "Último byte de memoria");
        
        $display("\n PRUEBA 6: Comportamiento durante reset");
        rst = 1;                       // Activa reset
        read(0, 4);                    // Intenta leer durante reset
        check(32'h00000000, "Lectura durante reset");
        rst = 0;                       // Desactiva reset
        
        $display("\n PRUEBA 7: Manejo de direcciones inválidas");
        read(4096, 4);                 // Dirección fuera del rango válido
        check(32'h00000000, "Dirección inválida");
        
        $display("\n" + "="*50);
        $display(" TODAS LAS PRUEBAS COMPLETADAS");
        $display("="*50 + "\n");
        
        $finish;  // Termina la simulación
    end
    
    //=================================================================
    // MONITOR PARA DEPURACIÓN (OPCIONAL)
    //=================================================================
    
    // Muestra el estado de las señales en cada cambio
    initial begin
        $display("\n Monitor de señales activado:");
        $monitor("Tiempo:%0t | Addr:0x%03X | WriteData:0x%08X | ReadData:0x%08X | Write:%b | Read:%b | Tamaño:%b%b%b | Unsigned:%b", 
                 $time, Address, WriteData, ReadData, MemWrite, MemRead, 
                 one_byte, two_byte, four_bytes, unsigned_load);
    end

    //=================================================================
    // GENERACIÓN DE ARCHIVOS DE ONDAS PARA VISUALIZACIÓN
    //=================================================================
    
    // Guarda todas las señales en un archivo VCD para ver las formas de onda
    initial begin
        $dumpfile("DataMemory_tb.vcd");
        $dumpvars(0, DataMemory_tb);
    end 
    
endmodule

Proyecto_3/src/build/DataMemory_tb.vcd
$date
	Sun Jun 08 15:48:37 2025
$end
$version
	Icarus Verilog
$end
$timescale
	1s
$end
$scope module DataMemory_tb $end
$var wire 32 ! ReadData [31:0] $end
$var parameter 32 " CLK_PERIOD $end
$var parameter 32 # DEPTH $end
$var parameter 32 $ WIDTH $end
$var reg 12 % Address [11:0] $end
$var reg 1 & MemRead $end
$var reg 1 ' MemWrite $end
$var reg 32 ( WriteData [31:0] $end
$var reg 1 ) clk $end
$var reg 1 * four_bytes $end
$var reg 1 + one_byte $end
$var reg 1 , rst $end
$var reg 1 - two_byte $end
$var reg 1 . unsigned_load $end
$scope module dut $end
$var wire 12 / Address [11:0] $end
$var wire 1 & MemRead $end
$var wire 1 ' MemWrite $end
$var wire 32 0 WriteData [31:0] $end
$var wire 1 ) clk $end
$var wire 1 * four_bytes $end
$var wire 8 1 mem_byte [7:0] $end
$var wire 1 + one_byte $end
$var wire 1 , rst $end
$var wire 1 - two_byte $end
$var wire 1 . unsigned_load $end
$var wire 1 2 valid_word_address $end
$var wire 1 3 valid_halfword_address $end
$var wire 1 4 valid_address $end
$var wire 32 5 mem_word [31:0] $end
$var wire 16 6 mem_halfword [15:0] $end
$var wire 32 7 halfword_unsigned [31:0] $end
$var wire 32 8 halfword_signed [31:0] $end
$var wire 32 9 byte_unsigned [31:0] $end
$var wire 32 : byte_signed [31:0] $end
$var parameter 32 ; DEPTH $end
$var parameter 32 < WIDTH $end
$var reg 32 = ReadData [31:0] $end
$upscope $end
$scope task check $end
$var reg 32 > expected [31:0] $end
$upscope $end
$scope task read $end
$var reg 12 ? addr [11:0] $end
$var reg 3 @ size [2:0] $end
$var reg 1 A unsign $end
$upscope $end
$scope task reset $end
$upscope $end
$scope task write $end
$var reg 12 B addr [11:0] $end
$var reg 32 C data [31:0] $end
$var reg 3 D size [2:0] $end
$upscope $end
$upscope $end
$enddefinitions $end
$comment Show the parameter values. $end
$dumpall
b100000 <
b1100 ;
b100000 $
b1100 #
b1010 "
$end
#0
$dumpvars
bx D
bx C
bx B
xA
bx @
bx ?
bx >
b0 =
bx :
b0xxxxxxxx 9
bx 8
b0xxxxxxxxxxxxxxxx 7
bx 6
bx 5
x4
x3
x2
bx 1
bx 0
bx /
x.
x-
1,
x+
x*
0)
bx (
x'
x&
bx %
b0 !
$end
#5
b100 D
b11011110101011011011111011101111 C
b0 B
0,
1)
#10
0)
#15
b11111111111111111111111111101111 :
b11101111 9
b11101111 1
b11111111111111111011111011101111 8
b1011111011101111 7
b1011111011101111 6
b11011110101011011011111011101111 5
0+
0-
1*
0.
0&
1'
b11011110101011011011111011101111 (
b11011110101011011011111011101111 0
14
13
12
b0 %
b0 /
1)
#20
0)
#25
0A
b100 @
b0 ?
0'
1)
#30
0)
#35
b11011110101011011011111011101111 !
b11011110101011011011111011101111 =
1&
1)
#40
0)
#45
b1 D
b11111111 C
b100 B
b11011110101011011011111011101111 >
1)
#50
0)
#55
b0 !
b0 =
1+
0*
0&
1'
b11111111 (
b11111111 0
b11111111111111111111111111111111 :
b11111111 9
b11111111 1
bx11111111 8
b0xxxxxxxx11111111 7
bx11111111 6
bx11111111 5
b100 %
b100 /
1)
#60
0)
#65
b1 @
b100 ?
0'
1)
#70
0)
#75
b11111111111111111111111111111111 !
b11111111111111111111111111111111 =
1&
1)
#80
0)
#85
1A
b11111111111111111111111111111111 >
1)
#90
0)
#95
b11111111 !
b11111111 =
1.
1)
#100
0)
#105
b10 D
b1111111111111111 C
b1000 B
b11111111 >
1)
#110
0)
#115
b0 !
b0 =
0+
1-
0.
0&
1'
b1111111111111111 (
b1111111111111111 0
b11111111111111111111111111111111 :
b11111111 9
b11111111 1
b11111111111111111111111111111111 8
b1111111111111111 7
b1111111111111111 6
bx1111111111111111 5
b1000 %
b1000 /
1)
#120
0)
#125
0A
b10 @
b1000 ?
0'
1)
#130
0)
#135
b11111111111111111111111111111111 !
b11111111111111111111111111111111 =
1&
1)
#140
0)
#145
1A
b11111111111111111111111111111111 >
1)
#150
0)
#155
b1111111111111111 !
b1111111111111111 =
1.
1)
#160
0)
#165
b100 D
b10010001101000101011001111000 C
b1100 B
b1111111111111111 >
1)
#170
0)
#175
b0 !
b0 =
0-
1*
0.
0&
1'
b10010001101000101011001111000 (
b10010001101000101011001111000 0
b1111000 :
b1111000 9
b1111000 1
b101011001111000 8
b101011001111000 7
b101011001111000 6
b10010001101000101011001111000 5
b1100 %
b1100 /
1)
#180
0)
#185
b1 @
b1100 ?
0'
1)
#190
0)
#195
b1111000 !
b1111000 =
1+
0*
1.
1&
1)
#200
0)
#205
b1101 ?
b1111000 >
1)
#210
0)
#215
b1010110 !
b1010110 =
b1010110 :
b1010110 9
b1010110 1
b11010001010110 8
b11010001010110 7
b11010001010110 6
bx000100100011010001010110 5
b1101 %
b1101 /
1)
#220
0)
#225
b10 @
b1100 ?
b1010110 >
1)
#230
0)
#235
b101011001111000 !
b101011001111000 =
0+
1-
b1111000 :
b1111000 9
b1111000 1
b101011001111000 8
b101011001111000 7
b101011001111000 6
b10010001101000101011001111000 5
b1100 %
b1100 /
1)
#240
0)
#245
b10101010101010101011101110111011 C
b111111111100 B
b101011001111000 >
1)
#250
0)
#255
b0 !
b0 =
0-
1*
0.
0&
1'
b10101010101010101011101110111011 (
b10101010101010101011101110111011 0
b11111111111111111111111110111011 :
b10111011 9
b10111011 1
b11111111111111111011101110111011 8
b1011101110111011 7
b1011101110111011 6
b10101010101010101011101110111011 5
b111111111100 %
b111111111100 /
1)
#260
0)
#265
0A
b100 @
b111111111100 ?
0'
1)
#270
0)
#275
b10101010101010101011101110111011 !
b10101010101010101011101110111011 =
1&
1)
#280
0)
#285
b1 D
b11001100110011001101110111011101 C
b111111111111 B
b10101010101010101011101110111011 >
1)
#290
0)
#295
b0 !
b0 =
1+
0*
0&
1'
b11001100110011001101110111011101 (
b11001100110011001101110111011101 0
03
02
b11111111111111111111111111011101 :
b11011101 9
b11011101 1
bx11011101 8
b0xxxxxxxx11011101 7
bx11011101 6
bx11011101 5
b111111111111 %
b111111111111 /
1)
#300
0)
#305
1A
b1 @
b111111111111 ?
0'
1)
#310
0)
#315
b11011101 !
b11011101 =
1.
1&
1)
#320
0)
#325
b0 !
b0 =
0A
b100 @
b0 ?
1,
b11011101 >
1)
#330
0)
#335
0+
1*
0.
13
12
b11111111111111111111111111101111 :
b11101111 9
b11101111 1
b11111111111111111011111011101111 8
b1011111011101111 7
b1011111011101111 6
b11011110101011011011111011101111 5
b0 %
b0 /
1)
#340
0)
#345
b11011110101011011011111011101111 !
b11011110101011011011111011101111 =
0,
b0 >
1)
