Proyecto_2/src/design/ImmediateGenerator.sv
// Generador de inmediatos para diferentes propósitos dentro del procesador componente combinacional
module ImmediateGenerator #(parameter WIDTH=32)
(
    input logic [6:0] Opcode,
    input logic [WIDTH-1:0] instruction,
    output logic [WIDTH-1:0] ImmExt
);

// Señales intermedias para evitar selecciones constantes en always_comb
logic [11:0] i_type_imm;
logic [11:0] s_type_imm;
logic [12:0] b_type_imm;
logic [19:0] u_type_imm;
logic [20:0] j_type_imm;

// Extraer campos de inmediatos fuera del always_comb
assign i_type_imm = instruction[31:20];
assign s_type_imm = {instruction[31:25], instruction[11:7]};
assign b_type_imm = {instruction[31], instruction[7], instruction[30:25], instruction[11:8], 1'b0};
assign u_type_imm = instruction[31:12];
assign j_type_imm = {instruction[31], instruction[19:12], instruction[20], instruction[30:21], 1'b0};

// Señales para extensión de signo
logic sign_i, sign_s, sign_b, sign_j;
assign sign_i = i_type_imm[11];
assign sign_s = s_type_imm[11];
assign sign_b = b_type_imm[12];
assign sign_j = j_type_imm[20];

always_comb begin
    case (Opcode)
        // Tipo I (e.g., lw, addi, jalr) - inmediato en [31:20] (12 bits)
        7'b0000011,  // LOAD
        7'b0010011,  // OP-IMM (addi, slti, etc.)
        7'b1100111:  // JALR
        begin
            ImmExt = {{(WIDTH-12){sign_i}}, i_type_imm};
        end
        
        // Tipo S (e.g., sw) - inmediato en [31:25] y [11:7]
        7'b0100011:  // STORE
        begin
            ImmExt = {{(WIDTH-12){sign_s}}, s_type_imm};
        end
        
        // Tipo B (e.g., beq, bne) - inmediato disperso: [31], [7], [30:25], [11:8]
        7'b1100011:  // BRANCH
        begin
            ImmExt = {{(WIDTH-13){sign_b}}, b_type_imm};
        end
        
        // Tipo U (e.g., lui, auipc) - inmediato en [31:12], parte baja en 0
        7'b0110111,  // LUI
        7'b0010111:  // AUIPC
        begin
            ImmExt = {u_type_imm, 12'b0};       // 20 bits superiores + 12 ceros
        end
        
        // Tipo J (e.g., jal) - inmediato disperso: [31], [19:12], [20], [30:21]
        7'b1101111:  // JAL
        begin
            ImmExt = {{(WIDTH-21){sign_j}}, j_type_imm};
        end
        
        // Default: todos los bits en 0
        default: ImmExt = {WIDTH{1'b0}};
    endcase
end

endmodule

Proyecto 3/src/sim/ImmediateGenerator_tb.sv
// Testbench corregido del ImmediateGenerator

`timescale 1ns/1ps

module ImmediateGenerator_tb;

    // Parámetros del testbench
    parameter WIDTH = 32;

    // Declaracion de las señales para el testbench.
    logic [6:0] Opcode;
    logic [WIDTH-1:0] instruction;
    logic [WIDTH-1:0] ImmExt;

    // Declaracion de las instancias para el testbench
    ImmediateGenerator #(.WIDTH(WIDTH)) uut (
        .Opcode(Opcode),
        .instruction(instruction),
        .ImmExt(ImmExt)
    );

    // Variables para verificación
    integer test_count = 0;
    integer pass_count = 0;
    
    // Task para verificar resultados con mejor formato
    task check_immediate;
        input [31:0] expected;
        input [31:0] actual;
        input [20*8:1] test_name;
        begin
            test_count = test_count + 1;
            if (expected == actual) begin
                $display("[PASS] %-25s: Expected=%0d (0x%08X), Got=%0d (0x%08X)", 
                        test_name, $signed(expected), expected, $signed(actual), actual);
                pass_count = pass_count + 1;
            end else begin
                $display("[FAIL] %-25s: Expected=%0d (0x%08X), Got=%0d (0x%08X)", 
                        test_name, $signed(expected), expected, $signed(actual), actual);
                $display("       Instrucción: 0x%08X, Bits inmediato: %b", 
                        instruction, instruction[31:20]); // Mostrar bits relevantes
            end
            #1; // Pequeña pausa para claridad
        end
    endtask
    
    initial begin
        $display("=== TESTBENCH CORREGIDO: RISC-V Immediate Generator ===");
        $display("Verificando generación correcta de inmediatos con extensión de signo\n");
        
        // ====== TIPO I (Opcode = 0010011) ======
        $display("--- Pruebas Tipo I (Inmediato) - Opcode: 0010011 ---");
        $display("Formato I: imm[11:0] = instruction[31:20]");
        
        // Caso 1: addi x4, x6, 30 (positivo)
        // imm = 30 = 12'b000000011110
        instruction = 32'b000000011110_00110_000_00100_0010011;
        Opcode = 7'b0010011;
        #10;
        check_immediate(32'd30, ImmExt, "I-Type: +30");
        
        // Caso 2: addi x5, x7, -10 (negativo)
        // imm = -10 = 12'b111111110110 (complemento a 2)
        instruction = 32'b111111110110_00111_000_00101_0010011;
        Opcode = 7'b0010011;
        #10;
        check_immediate(-32'd10, ImmExt, "I-Type: -10");
        
        // Caso 3: addi x3, x8, 2047 (máximo positivo)
        // imm = 2047 = 12'b011111111111
        instruction = 32'b011111111111_01000_000_00011_0010011;
        Opcode = 7'b0010011;
        #10;
        check_immediate(32'd2047, ImmExt, "I-Type: +2047");
        
        // Caso 4: addi x2, x9, -2048 (mínimo negativo)
        // imm = -2048 = 12'b100000000000
        instruction = 32'b100000000000_01001_000_00010_0010011;
        Opcode = 7'b0010011;
        #10;
        check_immediate(-32'd2048, ImmExt, "I-Type: -2048");
        
        // ====== TIPO I LOAD (Opcode = 0000011) ======
        $display("\n--- Pruebas Tipo I Load - Opcode: 0000011 ---");
        
        // Caso 1: lw x4, 16(x5)
        // imm = 16 = 12'b000000010000
        instruction = 32'b000000010000_00101_010_00100_0000011;
        Opcode = 7'b0000011;
        #10;
        check_immediate(32'd16, ImmExt, "I-Load: +16");
        
        // Caso 2: lb x3, -20(x6)
        // imm = -20 = 12'b111111101100
        instruction = 32'b111111101100_00110_000_00011_0000011;
        Opcode = 7'b0000011;
        #10;
        check_immediate(-32'd20, ImmExt, "I-Load: -20");
        
        // ====== TIPO S (Opcode = 0100011) ======
        $display("\n--- Pruebas Tipo S (Store) - Opcode: 0100011 ---");
        $display("Formato S: imm[11:0] = {instruction[31:25], instruction[11:7]}");
        
        // Caso 1: sw x5, 8(x6) (offset positivo)
        // imm = 8 = 12'b000000001000 = {7'b0000000, 5'b01000}
        instruction = 32'b0000000_00101_00110_010_01000_0100011;
        Opcode = 7'b0100011;
        #10;
        check_immediate(32'd8, ImmExt, "S-Type: +8");
        
        // Caso 2: sb x7, -12(x8) (offset negativo)
        // imm = -12 = 12'b111111110100 = {7'b1111111, 5'b10100}
        instruction = 32'b1111111_00111_01000_000_10100_0100011;
        Opcode = 7'b0100011;
        #10;
        check_immediate(-32'd12, ImmExt, "S-Type: -12");
        
        // Caso 3: sw x1, 2047(x2) (máximo positivo)
        // imm = 2047 = 12'b011111111111 = {7'b0111111, 5'b11111}
        instruction = 32'b0111111_00001_00010_010_11111_0100011;
        Opcode = 7'b0100011;
        #10;
        check_immediate(32'd2047, ImmExt, "S-Type: +2047");
        
        // Caso 4: sw x3, -2048(x4) (mínimo negativo)
        // imm = -2048 = 12'b100000000000 = {7'b1000000, 5'b00000}
        instruction = 32'b1000000_00011_00100_010_00000_0100011;
        Opcode = 7'b0100011;
        #10;
        check_immediate(-32'd2048, ImmExt, "S-Type: -2048");
        
        // ====== TIPO B (Opcode = 1100011) ======
        $display("\n--- Pruebas Tipo B (Branch) - Opcode: 1100011 ---");
        $display("Formato B: imm[12:1] = {instruction[31], instruction[7], instruction[30:25], instruction[11:8]}");
        $display("Nota: Inmediato B siempre es múltiplo de 2 (LSB = 0)");
        
        // Caso 1: beq x4, x5, 8 (salto hacia adelante)
        // imm = 8 = 13'b0000000001000, imm[12:1] = 12'b000000000100
        // {imm[12], imm[10:5], imm[4:1], imm[11]} = {0, 000000, 0100, 0}
        instruction = 32'b0_000000_00101_00100_000_0100_0_1100011;
        Opcode = 7'b1100011;
        #10;
        check_immediate(32'd8, ImmExt, "B-Type: +8");
        
        // Caso 2: bne x6, x7, -4 (salto hacia atrás)
        // imm = -4 = 13'b1111111111100, imm[12:1] = 12'b111111111110
        // {imm[12], imm[10:5], imm[4:1], imm[11]} = {1, 111111, 1110, 1}
        instruction = 32'b1_111111_00111_00110_001_1110_1_1100011;
        Opcode = 7'b1100011; 
        #10;
        check_immediate(-32'd4, ImmExt, "B-Type: -4");
        
        // Caso 3: beq x1, x2, 4094 (máximo positivo)
        // imm = 4094 = 13'b0111111111110, imm[12:1] = 12'b011111111111
        instruction = 32'b0_111111_00010_00001_000_1111_1_1100011;
        Opcode = 7'b1100011;
        #10;
        check_immediate(32'd4094, ImmExt, "B-Type: +4094");
        
        // Caso 4: bne x3, x4, -4096 (mínimo negativo)
        // imm = -4096 = 13'b1000000000000, imm[12:1] = 12'b100000000000
        instruction = 32'b1_000000_00100_00011_001_0000_0_1100011;
        Opcode = 7'b1100011;
        #10;
        check_immediate(-32'd4096, ImmExt, "B-Type: -4096");
        
        // ====== TIPO U LUI (Opcode = 0110111) ======
        $display("\n--- Pruebas Tipo U (LUI) - Opcode: 0110111 ---");
        $display("Formato U: imm[31:12] = instruction[31:12], imm[11:0] = 0");
        
        // Caso 1: lui x4, 0x12345
        instruction = 32'b00010010001101000101_00100_0110111;
        Opcode = 7'b0110111;
        #10;
        check_immediate(32'h12345000, ImmExt, "U-LUI: 0x12345");
        
        // Caso 2: lui x5, 0x80000 (bit de signo en 1)
        instruction = 32'b10000000000000000000_00101_0110111;
        Opcode = 7'b0110111;
        #10;
        check_immediate(32'h80000000, ImmExt, "U-LUI: 0x80000");
        
        // ====== TIPO U AUIPC (Opcode = 0010111) ======
        $display("\n--- Pruebas Tipo U (AUIPC) - Opcode: 0010111 ---");
        
        // Caso 1: auipc x5, 0x1000
        instruction = 32'b00000001000000000000_00101_0010111;
        Opcode = 7'b0010111;
        #10;
        check_immediate(32'h01000000, ImmExt, "U-AUIPC: 0x1000");
        
        // Caso 2: auipc x1, 0xFFFFF (todos 1s)
        instruction = 32'b11111111111111111111_00001_0010111;
        Opcode = 7'b0010111;
        #10;
        check_immediate(32'hFFFFF000, ImmExt, "U-AUIPC: 0xFFFFF");
        
        // ====== TIPO J (Opcode = 1101111) ======
        $display("\n--- Pruebas Tipo J (Jump) - Opcode: 1101111 ---");
        $display("Formato J: imm[20:1] = {instruction[31], instruction[19:12], instruction[20], instruction[30:21]}");
        $display("Nota: Inmediato J siempre es múltiplo de 2 (LSB = 0)");
        
        // Caso 1: jal x1, 16 (salto pequeño)
        // imm = 16 = 21'b000000000000000010000, imm[20:1] = 20'b00000000000000001000
        // {imm[20], imm[10:1], imm[11], imm[19:12]} = {0, 0000001000, 0, 00000000}
        instruction = 32'b0_0000001000_0_00000000_00001_1101111;
        Opcode = 7'b1101111;
        #10;
        check_immediate(32'd16, ImmExt, "J-Type: +16");
        
        // Caso 2: jal x2, -8 (salto negativo)
        // imm = -8 = 21'b111111111111111111000, imm[20:1] = 20'b11111111111111111100
        instruction = 32'b1_1111111100_1_11111111_00010_1101111;
        Opcode = 7'b1101111;
        #10;
        check_immediate(-32'd8, ImmExt, "J-Type: -8");
        
        // Caso 3: jal x3, 1048574 (máximo positivo)
        // imm = 1048574 = 21'b011111111111111111110
        instruction = 32'b0_1111111111_1_01111111_00011_1101111;
        Opcode = 7'b1101111;
        #10;
        check_immediate(32'd1048574, ImmExt, "J-Type: +1048574");
        
        // Caso 4: jal x4, -1048576 (mínimo negativo)
        // imm = -1048576 = 21'b100000000000000000000
        instruction = 32'b1_0000000000_0_00000000_00100_1101111;
        Opcode = 7'b1101111;
        #10;
        check_immediate(-32'd1048576, ImmExt, "J-Type: -1048576");
        
        // ====== CASOS ESPECIALES ======
        $display("\n--- Casos Especiales (Inmediatos Cero) ---");
        
        // Inmediato cero en cada tipo
        instruction = 32'b000000000000_00000_000_00000_0010011; // addi x0, x0, 0
        Opcode = 7'b0010011;
        #10;
        check_immediate(32'd0, ImmExt, "I-Type: Zero");
        
        instruction = 32'b0000000_00000_00000_010_00000_0100011; // sw x0, 0(x0)
        Opcode = 7'b0100011;
        #10;
        check_immediate(32'd0, ImmExt, "S-Type: Zero");
        
        instruction = 32'b0_000000_00000_00000_000_0000_0_1100011; // beq x0, x0, 0
        Opcode = 7'b1100011;
        #10;
        check_immediate(32'd0, ImmExt, "B-Type: Zero");
        
        instruction = 32'b00000000000000000000_00000_0110111; // lui x0, 0
        Opcode = 7'b0110111;
        #10;
        check_immediate(32'd0, ImmExt, "U-Type: Zero");
        
        instruction = 32'b0_0000000000_0_00000000_00000_1101111; // jal x0, 0
        Opcode = 7'b1101111;
        #10;
        check_immediate(32'd0, ImmExt, "J-Type: Zero");
        
        // ====== CASOS ADICIONALES PARA MAYOR COBERTURA ======
        $display("\n--- Casos Adicionales ---");
        
        // Caso límite: I-type con bit 11 = 1 (signo negativo)
        instruction = 32'b100000000001_00001_000_00010_0010011; // addi x2, x1, -2047
        Opcode = 7'b0010011;
        #10;
        check_immediate(-32'd2047, ImmExt, "I-Type: -2047");
        
        // Caso U-type con valor intermedio
        instruction = 32'b01010101010101010101_00011_0110111; // lui x3, 0x55555
        Opcode = 7'b0110111;
        #10;
        check_immediate(32'h55555000, ImmExt, "U-Type: 0x55555");
        
        // ====== PRUEBA CON Opcode INVÁLIDO ======
        $display("\n--- Prueba con Opcode Inválido ---");
        instruction = 32'h12345678;
        Opcode = 7'b1111111; // Opcode inválido
        #10;
        check_immediate(32'd0, ImmExt, "Invalid Opcode");
        
        // Reporte final
        $display("\n" + "="*50);
        $display("=== RESUMEN DE PRUEBAS ===");
        $display("Total de pruebas: %d", test_count);
        $display("Pruebas exitosas: %d", pass_count);
        $display("Pruebas fallidas: %d", test_count - pass_count);
        $display("Porcentaje de éxito: %.1f%%", (pass_count * 100.0) / test_count);
        
        if (pass_count == test_count) begin
            $display("\n¡TODAS LAS PRUEBAS PASARON! ✓");
            $display("El generador de inmediatos funciona correctamente.");
        end else begin
            $display("\nALGUNAS PRUEBAS FALLARON - Revisar implementación ✗");
            $display("Verificar la lógica de generación de inmediatos.");
        end
        
        $display("="*50);
        $finish;
    end

    // Sistema de guardado de los resultados del testbench.
    initial begin
        $dumpfile("ImmediateGenerator_tb.vcd");
        $dumpvars(0, ImmediateGenerator_tb);
    end 

endmodule

Proyecto_3/src/build/ImmediateGenerator_tb.vcd
$date
	Sun Jun 08 15:54:59 2025
$end
$version
	Icarus Verilog
$end
$timescale
	1ps
$end
$scope module ImmediateGenerator_tb $end
$var wire 32 ! ImmExt [31:0] $end
$var parameter 32 " WIDTH $end
$var reg 7 # Opcode [6:0] $end
$var reg 32 $ instruction [31:0] $end
$var integer 32 % pass_count [31:0] $end
$var integer 32 & test_count [31:0] $end
$scope module uut $end
$var wire 7 ' Opcode [6:0] $end
$var wire 32 ( instruction [31:0] $end
$var wire 20 ) u_type_imm [19:0] $end
$var wire 1 * sign_s $end
$var wire 1 + sign_j $end
$var wire 1 , sign_i $end
$var wire 1 - sign_b $end
$var wire 12 . s_type_imm [11:0] $end
$var wire 21 / j_type_imm [20:0] $end
$var wire 12 0 i_type_imm [11:0] $end
$var wire 13 1 b_type_imm [12:0] $end
$var parameter 32 2 WIDTH $end
$var reg 32 3 ImmExt [31:0] $end
$upscope $end
$scope task check_immediate $end
$var reg 32 4 actual [31:0] $end
$var reg 32 5 expected [31:0] $end
$var reg 160 6 test_name [160:1] $end
$upscope $end
$upscope $end
$enddefinitions $end
$comment Show the parameter values. $end
$dumpall
b100000 2
b100000 "
$end
#0
$dumpvars
bx 6
bx 5
bx 4
b11110 3
b100 1
b11110 0
b110000000000011110 /
b100 .
0-
0,
0+
0*
b1111000110000 )
b1111000110000001000010011 (
b10011 '
b0 &
b0 %
b1111000110000001000010011 $
b10011 #
b11110 !
$end
#10000
b1 %
b1 &
b100100100101101010101000111100101110000011001010011101000100000001010110011001100110000 6
b11110 4
b11110 5
#11000
1,
1*
1-
1+
b11111111111111111111111111110110 !
b11111111111111111111111111110110 3
b111111110110 0
b111111100101 .
b1111111100100 1
b11111111011000111000 )
b100111000011111110110 /
b11111111011000111000001010010011 $
b11111111011000111000001010010011 (
#21000
b10 %
b10 &
b100100100101101010101000111100101110000011001010011101000100000001011010011000100110000 6
b11111111111111111111111111110110 4
b11111111111111111111111111110110 5
#22000
0,
0*
0-
0+
b11111111111 !
b11111111111 3
b11111111111 0
b11111100011 .
b111111100010 1
b1111111111101000000 )
b1000000111111111110 /
b1111111111101000000000110010011 $
b1111111111101000000000110010011 (
#32000
b11 %
b11 &
b1001001001011010101010001111001011100000110010100111010001000000010101100110010001100000011010000110111 6
b11111111111 4
b11111111111 5
#33000
1,
1*
1-
1+
b11111111111111111111100000000000 !
b11111111111111111111100000000000 3
b100000000000 0
b100000000010 .
b1000000000010 1
b10000000000001001000 )
b101001000000000000000 /
b10000000000001001000000100010011 $
b10000000000001001000000100010011 (
#43000
b100 %
b100 &
b1001001001011010101010001111001011100000110010100111010001000000010110100110010001100000011010000111000 6
b11111111111111111111100000000000 4
b11111111111111111111100000000000 5
#44000
0,
0*
0-
0+
b10000 !
b10000 3
b10000 0
b100 .
b100 1
b1000000101010 )
b101010000000010000 /
b11 #
b11 '
b1000000101010001000000011 $
b1000000101010001000000011 (
#54000
b101 %
b101 &
b100100100101101010011000110111101100001011001000011101000100000001010110011000100110110 6
b10000 4
b10000 5
#55000
1,
1*
1-
1+
b11111111111111111111111111101100 !
b11111111111111111111111111101100 3
b111111101100 0
b111111100011 .
b1111111100010 1
b11111110110000110000 )
b100110000011111101100 /
b11111110110000110000000110000011 $
b11111110110000110000000110000011 (
#65000
b110 %
b110 &
b100100100101101010011000110111101100001011001000011101000100000001011010011001000110000 6
b11111111111111111111111111101100 4
b11111111111111111111111111101100 5
#66000
0,
0*
0-
0+
b1000 !
b1000 3
b101 0
b1000 .
b1000 1
b10100110010 )
b110010100000000100 /
b100011 #
b100011 '
b10100110010010000100011 $
b10100110010010000100011 (
#76000
b111 %
b111 &
b1010011001011010101010001111001011100000110010100111010001000000010101100111000 6
b1000 4
b1000 5
#77000
1,
1*
1-
1+
b11111111111111111111111111110100 !
b11111111111111111111111111110100 3
b111111100111 0
b111111110100 .
b1011111110100 1
b11111110011101000000 )
b101000000111111100110 /
b11111110011101000000101000100011 $
b11111110011101000000101000100011 (
#87000
b1000 %
b1000 &
b101001100101101010101000111100101110000011001010011101000100000001011010011000100110010 6
b11111111111111111111111111110100 4
b11111111111111111111111111110100 5
#88000
0,
0*
0-
0+
b11111111111 !
b11111111111 3
b11111100001 0
b11111111111 .
b111111111110 1
b1111110000100010010 )
b10010111111100000 /
b1111110000100010010111110100011 $
b1111110000100010010111110100011 (
#98000
b1001 %
b1001 &
b1010011001011010101010001111001011100000110010100111010001000000010101100110010001100000011010000110111 6
b11111111111 4
b11111111111 5
#99000
1,
1*
1-
1+
b11111111111111111111100000000000 !
b11111111111111111111100000000000 3
b100000000011 0
b100000000000 .
b1000000000000 1
b10000000001100100010 )
b100100010100000000010 /
b10000000001100100010000000100011 $
b10000000001100100010000000100011 (
#109000
b1010 %
b1010 &
b1010011001011010101010001111001011100000110010100111010001000000010110100110010001100000011010000111000 6
b11111111111111111111100000000000 4
b11111111111111111111100000000000 5
#110000
0,
0*
0-
0+
b1000 !
b1000 3
b101 0
b1000 .
b1000 1
b10100100000 )
b100000100000000100 /
b1100011 #
b1100011 '
b10100100000010001100011 $
b10100100000010001100011 (
#120000
b1011 %
b1011 &
b1000010001011010101010001111001011100000110010100111010001000000010101100111000 6
b1000 4
b1000 5
#121000
1,
1*
1-
1+
b11111111111111111111111111111100 !
b11111111111111111111111111111100 3
b111111100111 0
b111111111101 .
b1111111111100 1
b11111110011100110001 )
b100110001111111100110 /
b11111110011100110001111011100011 $
b11111110011100110001111011100011 (
#131000
b1100 %
b1100 &
b1000010001011010101010001111001011100000110010100111010001000000010110100110100 6
b11111111111111111111111111111100 4
b11111111111111111111111111111100 5
#132000
0,
0*
0-
0+
b111111111110 !
b111111111110 3
b11111100010 0
b11111111111 .
b111111111110 1
b1111110001000001000 )
b1000011111100010 /
b1111110001000001000111111100011 $
b1111110001000001000111111100011 (
#142000
b1101 %
b1101 &
b1000010001011010101010001111001011100000110010100111010001000000010101100110100001100000011100100110100 6
b111111111110 4
b111111111110 5
#143000
1,
1*
1-
1+
b11111111111111111111000000000000 !
b11111111111111111111000000000000 3
b100000000100 0
b100000000000 .
b1000000000000 1
b10000000010000011001 )
b100011001000000000100 /
b10000000010000011001000001100011 $
b10000000010000011001000001100011 (
#153000
b1110 %
b1110 &
b1000010001011010101010001111001011100000110010100111010001000000010110100110100001100000011100100110110 6
b11111111111111111111000000000000 4
b11111111111111111111000000000000 5
#154000
0,
0*
0-
0+
b10010001101000101000000000000 !
b10010001101000101000000000000 3
b100100011 0
b100100100 .
b100100100 1
b10010001101000101 )
b1000101100100100010 /
b110111 #
b110111 '
b10010001101000101001000110111 $
b10010001101000101001000110111 (
#164000
b1111 %
b1111 &
b101010100101101010011000101010101001001001110100010000000110000011110000011000100110010001100110011010000110101 6
b10010001101000101000000000000 4
b10010001101000101000000000000 5
#165000
1,
1*
1-
1+
b10000000000000000000000000000000 !
b10000000000000000000000000000000 3
b100000000000 0
b100000000101 .
b1100000000100 1
b10000000000000000000 )
b100000000000000000000 /
b10000000000000000000001010110111 $
b10000000000000000000001010110111 (
#175000
b10000 %
b10000 &
b101010100101101010011000101010101001001001110100010000000110000011110000011100000110000001100000011000000110000 6
b10000000000000000000000000000000 4
b10000000000000000000000000000000 5
#176000
0,
0*
0-
0+
b1000000000000000000000000 !
b1000000000000000000000000 3
b10000 0
b101 .
b100000000100 1
b1000000000000 )
b10000 /
b10111 #
b10111 '
b1000000000000001010010111 $
b1000000000000001010010111 (
#186000
b10001 %
b10001 &
b10101010010110101000001010101010100100101010000010000110011101000100000001100000111100000110001001100000011000000110000 6
b1000000000000000000000000 4
b1000000000000000000000000 5
#187000
1,
1*
1-
1+
b11111111111111111111000000000000 !
b11111111111111111111000000000000 3
b111111111111 0
b111111100001 .
b1111111100000 1
b11111111111111111111 )
b111111111111111111110 /
b11111111111111111111000010010111 $
b11111111111111111111000010010111 (
#197000
b10010 %
b10010 &
b1010101001011010100000101010101010010010101000001000011001110100010000000110000011110000100011001000110010001100100011001000110 6
b11111111111111111111000000000000 4
b11111111111111111111000000000000 5
#198000
0,
0*
0-
0+
b10000 !
b10000 3
b10000 0
b1 .
b100000000000 1
b1000000000000 )
b10000 /
b1101111 #
b1101111 '
b1000000000000000011101111 $
b1000000000000000011101111 (
#208000
b10011 %
b10011 &
b100101000101101010101000111100101110000011001010011101000100000001010110011000100110110 6
b10000 4
b10000 5
#209000
1,
1*
1-
1+
b11111111111111111111111111111000 !
b11111111111111111111111111111000 3
b111111111001 0
b111111100010 .
b1011111100010 1
b11111111100111111111 )
b111111111111111111000 /
b11111111100111111111000101101111 $
b11111111100111111111000101101111 (
#219000
b10100 %
b10100 &
b1001010001011010101010001111001011100000110010100111010001000000010110100111000 6
b11111111111111111111111111111000 4
b11111111111111111111111111111000 5
#220000
0,
0*
0-
0+
b1111111111111111110 !
b1111111111111111110 3
b11111111111 0
b11111100011 .
b111111100010 1
b1111111111101111111 )
b1111111111111111110 /
b1111111111101111111000111101111 $
b1111111111101111111000111101111 (
#230000
b10101 &
b1001010001011010101010001111001011100000110010100111010001000000010101100110001001100000011010000111000001101010011011100110100 6
b1111111111111111110 4
b11111111111111111110 5
#231000
1,
1*
1-
1+
b11111111111100000000000000000000 !
b11111111111100000000000000000000 3
b100000000000 0
b100000000100 .
b1000000000100 1
b10000000000000000000 )
b100000000000000000000 /
b10000000000000000000001001101111 $
b10000000000000000000001001101111 (
#241000
b10101 %
b10110 &
b1001010001011010101010001111001011100000110010100111010001000000010110100110001001100000011010000111000001101010011011100110110 6
b11111111111100000000000000000000 4
b11111111111100000000000000000000 5
#242000
0,
0*
0-
0+
b0 !
b0 3
b0 0
b0 .
b0 1
b0 )
b0 /
b10011 #
b10011 '
b10011 $
b10011 (
#252000
b10110 %
b10111 &
b10010010010110101010100011110010111000001100101001110100010000001011010011001010111001001101111 6
b0 4
b0 5
#253000
b10 )
b10000000000000 /
b100011 #
b100011 '
b10000000100011 $
b10000000100011 (
#263000
b10111 %
b11000 &
b10100110010110101010100011110010111000001100101001110100010000001011010011001010111001001101111 6
#264000
b0 )
b0 /
b1100011 #
b1100011 '
b1100011 $
b1100011 (
#274000
b11000 %
b11001 &
b10000100010110101010100011110010111000001100101001110100010000001011010011001010111001001101111 6
#275000
b110111 #
b110111 '
b110111 $
b110111 (
#285000
b11001 %
b11010 &
b10101010010110101010100011110010111000001100101001110100010000001011010011001010111001001101111 6
#286000
b1101111 #
b1101111 '
b1101111 $
b1101111 (
#296000
b11010 %
b11011 &
b10010100010110101010100011110010111000001100101001110100010000001011010011001010111001001101111 6
#297000
1,
1*
1-
1+
b11111111111111111111100000000001 !
b11111111111111111111100000000001 3
b100000000001 0
b100000000010 .
b1000000000010 1
b10000000000100001000 )
b100001000100000000000 /
b10011 #
b10011 '
b10000000000100001000000100010011 $
b10000000000100001000000100010011 (
#307000
b11011 %
b11100 &
b1001001001011010101010001111001011100000110010100111010001000000010110100110010001100000011010000110111 6
b11111111111111111111100000000001 4
b11111111111111111111100000000001 5
#308000
0,
0*
0-
0+
b1010101010101010101000000000000 !
b1010101010101010101000000000000 3
b10101010101 0
b10101000011 .
b110101000010 1
b1010101010101010101 )
b1010101110101010100 /
b110111 #
b110111 '
b1010101010101010101000110110111 $
b1010101010101010101000110110111 (
#318000
b11100 %
b11101 &
b10101010010110101010100011110010111000001100101001110100010000000110000011110000011010100110101001101010011010100110101 6
b1010101010101010101000000000000 4
b1010101010101010101000000000000 5
#319000
b0 !
b0 3
b100100011 0
b100101100 .
b100101100 1
b10010001101000101 )
b1000101100100100010 /
b1111111 #
b1111111 '
b10010001101000101011001111000 $
b10010001101000101011001111000 (
#329000
b11101 %
b11110 &
b100100101101110011101100110000101101100011010010110010000100000010011110111000001100011011011110110010001100101 6
b0 4
b0 5
