Proyecto_3/src/design/RegisterFile.sv
// Banco de registros del procesador RISC-V
// Se utiliza para escribir, leer y guardar los valores de los registros del procesador
module RegisterFile #(parameter WIDTH=32, parameter ADDR_WIDTH=5) (
    // Señales de entrada y salida
    input logic clk, rst, 
    input logic RegWrite,                           // Señal de control para escribir
    input logic [ADDR_WIDTH-1:0] Rs1, Rs2, Rd,    // Direcciones de registros fuente y destino
    input logic [WIDTH-1:0] WriteData,             // Dato a escribir
    output logic [WIDTH-1:0] ReadData1, ReadData2  // Datos leídos de Rs1 y Rs2
);

    // Banco de 32 registros de 32 bits cada uno (RISC-V estándar)
    logic [WIDTH-1:0] Registers [31:0];

    // Escritura síncrona
    always_ff @(posedge clk) begin
        if (rst) begin
            // Reset: todos los registros a 0
            for (int i = 0; i < 32; i++) begin
                Registers[i] <= {WIDTH{1'b0}};
            end
        end
        else begin
            // Escribir solo si RegWrite está activo y no es el registro x0
            if (RegWrite && (Rd != 5'b00000)) begin
                Registers[Rd] <= WriteData;
            end
        end
    end

    // Lectura combinacional (asíncrona)
    always_comb begin
        // ReadData1: Si Rs1 es x0, retorna 0, sino retorna el contenido del registro
        ReadData1 = (Rs1 == 5'b00000) ? {WIDTH{1'b0}} : Registers[Rs1];
        
        // ReadData2: Si Rs2 es x0, retorna 0, sino retorna el contenido del registro  
        ReadData2 = (Rs2 == 5'b00000) ? {WIDTH{1'b0}} : Registers[Rs2];
    end

endmodule

Proyecto 3/src/sim/RegisterFile_tb.sv
// Testbench  para el módulo RegisterFile
`timescale 1ns/1ps
module RegisterFile_tb #(parameter WIDTH=32, parameter ADDR_WIDTH=5) ();
  


  
  // Señales del testbench
  reg clk;
  reg rst;
  reg RegWrite;
  reg [ADDR_WIDTH-1:0] Rs1, Rs2, Rd;
  reg [WIDTH-1:0] WriteData;
  wire [WIDTH-1:0] ReadData1, ReadData2;
  
  // Variables para verificación
  integer error;
  integer finish_flag;
  integer i;
  
  // Modelo de referencia del banco de registros para verificación
  reg [WIDTH-1:0] reg_file_checker [0:31];
  
  // Instanciación del DUT (Device Under Test)
  RegisterFile #(
    .WIDTH(WIDTH), 
    .ADDR_WIDTH(ADDR_WIDTH)
  ) dut_reg_file (
    .clk(clk),
    .rst(rst),
    .RegWrite(RegWrite),
    .Rs1(Rs1),
    .Rs2(Rs2),
    .Rd(Rd),
    .WriteData(WriteData),
    .ReadData1(ReadData1),
    .ReadData2(ReadData2)
  );
  
  // Generación del reloj
  initial begin
    clk = 0;
    forever #5 clk = ~clk; // Período de 10ns
  end
  
  // Inicialización
  initial begin
    // Inicializar señales
    WriteData = 0;
    Rd = 0;
    RegWrite = 0;
    Rs1 = 0;
    Rs2 = 0;
    error = 0;
    finish_flag = 0;
    
    // Inicializar modelo de referencia
    for (i = 0; i < 32; i = i + 1) begin
      reg_file_checker[i] = 0;
    end
    
    
    // Ejecutar las pruebas
    test_sequence();
  end
  
  // Secuencia principal de pruebas
  task test_sequence;
    begin
      $display("=== Iniciando pruebas del RegisterFile ===");
      
      // Reset inicial
      rst = 1;
      repeat(3) @(posedge clk);
      rst = 0;
      @(posedge clk);
      
      // Fase 1: Escribir valores en todos los registros
      $display("Fase 1: Escribiendo en registros 0-31");
      test_write_all_registers();
      
      // Fase 2: Leer registros
      $display("Fase 2: Leyendo registros");
      test_read_registers();
      
      // Fase 3: Prueba del registro x0
      $display("Fase 3: Probando registro x0 (debe ser siempre 0)");
      test_register_zero();
      
      // Fase 4: Prueba de reset
      $display("Fase 4: Probando reset");
      test_reset();
      
      // Finalizar
      repeat(10) @(posedge clk);
      
      if (error == 0) begin
        $display("*** TODAS LAS PRUEBAS PASARON EXITOSAMENTE ***");
      end else begin
        $display("*** SE ENCONTRARON %d ERRORES EN LAS PRUEBAS ***", error);
      end
      
      finish_flag = 1;
      $finish;
    end
  endtask
  
  // Task para escribir en todos los registros
  task test_write_all_registers;
    begin
      for (i = 0; i < 32; i = i + 1) begin
        @(negedge clk);
        WriteData = i * 4 + 100;
        Rd = i;
        RegWrite = 1;
        
        // Actualizar modelo de referencia
        if (i != 0) begin
          reg_file_checker[i] = WriteData;
        end
        
        @(posedge clk);
        #1; // Pequeño delay
      end
      
      RegWrite = 0; // Deshabilitar escritura
    end
  endtask
  
  // Task para leer registros
  task test_read_registers;
    begin
      // Leer registros de manera secuencial
      for (i = 0; i < 31; i = i + 1) begin
        @(negedge clk);
        Rs1 = i;
        Rs2 = i + 1;
        @(posedge clk);
        #1; // Esperar estabilización
        
        // Verificar ReadData1
        if (i == 0) begin
          if (ReadData1 !== 32'h0) begin
            $display("[ERROR] ReadData1 debería ser 0 cuando Rs1=0, pero es %h", ReadData1);
            error = error + 1;
          end
        end else begin
          if (ReadData1 !== reg_file_checker[i]) begin
            $display("[ERROR] ReadData1 mismatch: Rs1=%d, Expected=%h, Got=%h", 
                    i, reg_file_checker[i], ReadData1);
            error = error + 1;
          end
        end
        
        // Verificar ReadData2
        if ((i + 1) < 32) begin
          if ((i + 1) == 0) begin
            if (ReadData2 !== 32'h0) begin
              $display("[ERROR] ReadData2 debería ser 0 cuando Rs2=0, pero es %h", ReadData2);
              error = error + 1;
            end
          end else begin
            if (ReadData2 !== reg_file_checker[i + 1]) begin
              $display("[ERROR] ReadData2 mismatch: Rs2=%d, Expected=%h, Got=%h", 
                      i + 1, reg_file_checker[i + 1], ReadData2);
              error = error + 1;
            end
          end
        end
      end
    end
  endtask
  
  // Task para probar el registro x0
  task test_register_zero;
    begin
      // Intentar escribir en el registro x0
      @(negedge clk);
      WriteData = 32'hDEADBEEF;
      Rd = 0;
      RegWrite = 1;
      @(posedge clk);
      
      // Leer el registro x0
      @(negedge clk);
      RegWrite = 0;
      Rs1 = 0;
      Rs2 = 0;
      @(posedge clk);
      #1;
      
      // Verificar que sigue siendo 0
      if (ReadData1 !== 32'h0) begin
        $display("[ERROR] Registro x0 no es 0 después de intento de escritura: %h", ReadData1);
        error = error + 1;
      end
      
      if (ReadData2 !== 32'h0) begin
        $display("[ERROR] Registro x0 no es 0 en ReadData2: %h", ReadData2);
        error = error + 1;
      end
    end
  endtask
  
  // Task para probar el reset
  task test_reset;
    begin
      // Aplicar reset
      @(negedge clk);
      rst = 1;
      repeat(3) @(posedge clk);
      rst = 0;
      
      // Actualizar modelo de referencia
      for (i = 0; i < 32; i = i + 1) begin
        reg_file_checker[i] = 0;
      end
      
      // Verificar que todos los registros estén en 0
      for (i = 0; i < 32; i = i + 1) begin
        @(negedge clk);
        Rs1 = i;
        Rs2 = (i + 1) % 32;
        @(posedge clk);
        #1;
        
        if (ReadData1 !== 32'h0) begin
          $display("[ERROR] Registro %d no es 0 después del reset: %h", i, ReadData1);
          error = error + 1;
        end
      end
    end
  endtask
  
  // Monitor para verificación continua
  always @(posedge clk) begin
    if (!rst && RegWrite && (Rd != 5'b00000)) begin
      #1; // Pequeño delay para sincronización
      reg_file_checker[Rd] = WriteData;
    end
  end
  
  // Timeout de seguridad
  initial begin
    #100000; // 100us timeout
    if (!finish_flag) begin
      $display("[ERROR] Timeout - La simulación no terminó correctamente");
      $finish;
    end
  end
  
  // Inicio de la simulación
  initial begin
    // Configurar volcado de ondas (opcional)
    $dumpfile("RegisterFile_tb.vcd");
    $dumpvars(0, RegisterFile_tb);
    

  end
  
endmodule

Proyecto_3/src/build/RegisterFile_tb.vcd
$date
	Sun Jun 08 16:00:41 2025
$end
$version
	Icarus Verilog
$end
$timescale
	1ps
$end
$scope module RegisterFile_tb $end
$var wire 32 ! ReadData2 [31:0] $end
$var wire 32 " ReadData1 [31:0] $end
$var parameter 32 # ADDR_WIDTH $end
$var parameter 32 $ WIDTH $end
$var reg 5 % Rd [4:0] $end
$var reg 1 & RegWrite $end
$var reg 5 ' Rs1 [4:0] $end
$var reg 5 ( Rs2 [4:0] $end
$var reg 32 ) WriteData [31:0] $end
$var reg 1 * clk $end
$var reg 1 + rst $end
$var integer 32 , error [31:0] $end
$var integer 32 - finish_flag [31:0] $end
$var integer 32 . i [31:0] $end
$scope module dut_reg_file $end
$var wire 5 / Rd [4:0] $end
$var wire 1 & RegWrite $end
$var wire 5 0 Rs1 [4:0] $end
$var wire 5 1 Rs2 [4:0] $end
$var wire 32 2 WriteData [31:0] $end
$var wire 1 * clk $end
$var wire 1 + rst $end
$var parameter 32 3 ADDR_WIDTH $end
$var parameter 32 4 WIDTH $end
$var reg 32 5 ReadData1 [31:0] $end
$var reg 32 6 ReadData2 [31:0] $end
$scope begin $ivl_for_loop0 $end
$var integer 32 7 i [31:0] $end
$upscope $end
$upscope $end
$scope task test_read_registers $end
$upscope $end
$scope task test_register_zero $end
$upscope $end
$scope task test_reset $end
$upscope $end
$scope task test_sequence $end
$upscope $end
$scope task test_write_all_registers $end
$upscope $end
$upscope $end
$enddefinitions $end
$comment Show the parameter values. $end
$dumpall
b100000 4
b101 3
b100000 $
b101 #
$end
#0
$dumpvars
b0 7
b0 6
b0 5
b0 2
b0 1
b0 0
b0 /
b100000 .
b0 -
b0 ,
1+
0*
b0 )
b0 (
b0 '
0&
b0 %
b0 "
b0 !
$end
#5000
b100000 7
1*
#10000
0*
#15000
b100000 7
1*
#20000
0*
#25000
b100000 7
0+
1*
#30000
0*
#35000
b0 .
1*
#40000
1&
b1100100 )
b1100100 2
0*
#45000
1*
#46000
b1 .
#50000
b1 %
b1 /
b1101000 )
b1101000 2
0*
#55000
1*
#56000
b10 .
#60000
b10 %
b10 /
b1101100 )
b1101100 2
0*
#65000
1*
#66000
b11 .
#70000
b11 %
b11 /
b1110000 )
b1110000 2
0*
#75000
1*
#76000
b100 .
#80000
b100 %
b100 /
b1110100 )
b1110100 2
0*
#85000
1*
#86000
b101 .
#90000
b101 %
b101 /
b1111000 )
b1111000 2
0*
#95000
1*
#96000
b110 .
#100000
b110 %
b110 /
b1111100 )
b1111100 2
0*
#105000
1*
#106000
b111 .
#110000
b111 %
b111 /
b10000000 )
b10000000 2
0*
#115000
1*
#116000
b1000 .
#120000
b1000 %
b1000 /
b10000100 )
b10000100 2
0*
#125000
1*
#126000
b1001 .
#130000
b1001 %
b1001 /
b10001000 )
b10001000 2
0*
#135000
1*
#136000
b1010 .
#140000
b1010 %
b1010 /
b10001100 )
b10001100 2
0*
#145000
1*
#146000
b1011 .
#150000
b1011 %
b1011 /
b10010000 )
b10010000 2
0*
#155000
1*
#156000
b1100 .
#160000
b1100 %
b1100 /
b10010100 )
b10010100 2
0*
#165000
1*
#166000
b1101 .
#170000
b1101 %
b1101 /
b10011000 )
b10011000 2
0*
#175000
1*
#176000
b1110 .
#180000
b1110 %
b1110 /
b10011100 )
b10011100 2
0*
#185000
1*
#186000
b1111 .
#190000
b1111 %
b1111 /
b10100000 )
b10100000 2
0*
#195000
1*
#196000
b10000 .
#200000
b10000 %
b10000 /
b10100100 )
b10100100 2
0*
#205000
1*
#206000
b10001 .
#210000
b10001 %
b10001 /
b10101000 )
b10101000 2
0*
#215000
1*
#216000
b10010 .
#220000
b10010 %
b10010 /
b10101100 )
b10101100 2
0*
#225000
1*
#226000
b10011 .
#230000
b10011 %
b10011 /
b10110000 )
b10110000 2
0*
#235000
1*
#236000
b10100 .
#240000
b10100 %
b10100 /
b10110100 )
b10110100 2
0*
#245000
1*
#246000
b10101 .
#250000
b10101 %
b10101 /
b10111000 )
b10111000 2
0*
#255000
1*
#256000
b10110 .
#260000
b10110 %
b10110 /
b10111100 )
b10111100 2
0*
#265000
1*
#266000
b10111 .
#270000
b10111 %
b10111 /
b11000000 )
b11000000 2
0*
#275000
1*
#276000
b11000 .
#280000
b11000 %
b11000 /
b11000100 )
b11000100 2
0*
#285000
1*
#286000
b11001 .
#290000
b11001 %
b11001 /
b11001000 )
b11001000 2
0*
#295000
1*
#296000
b11010 .
#300000
b11010 %
b11010 /
b11001100 )
b11001100 2
0*
#305000
1*
#306000
b11011 .
#310000
b11011 %
b11011 /
b11010000 )
b11010000 2
0*
#315000
1*
#316000
b11100 .
#320000
b11100 %
b11100 /
b11010100 )
b11010100 2
0*
#325000
1*
#326000
b11101 .
#330000
b11101 %
b11101 /
b11011000 )
b11011000 2
0*
#335000
1*
#336000
b11110 .
#340000
b11110 %
b11110 /
b11011100 )
b11011100 2
0*
#345000
1*
#346000
b11111 .
#350000
b11111 %
b11111 /
b11100000 )
b11100000 2
0*
#355000
1*
#356000
0&
b0 .
#360000
b1101000 !
b1101000 6
b1 (
b1 1
0*
#365000
1*
#366000
b1 .
#370000
b1101100 !
b1101100 6
b1101000 "
b1101000 5
b10 (
b10 1
b1 '
b1 0
0*
#375000
1*
#376000
b10 .
#380000
b1110000 !
b1110000 6
b1101100 "
b1101100 5
b11 (
b11 1
b10 '
b10 0
0*
#385000
1*
#386000
b11 .
#390000
b1110100 !
b1110100 6
b1110000 "
b1110000 5
b100 (
b100 1
b11 '
b11 0
0*
#395000
1*
#396000
b100 .
#400000
b1111000 !
b1111000 6
b1110100 "
b1110100 5
b101 (
b101 1
b100 '
b100 0
0*
#405000
1*
#406000
b101 .
#410000
b1111100 !
b1111100 6
b1111000 "
b1111000 5
b110 (
b110 1
b101 '
b101 0
0*
#415000
1*
#416000
b110 .
#420000
b10000000 !
b10000000 6
b1111100 "
b1111100 5
b111 (
b111 1
b110 '
b110 0
0*
#425000
1*
#426000
b111 .
#430000
b10000100 !
b10000100 6
b10000000 "
b10000000 5
b1000 (
b1000 1
b111 '
b111 0
0*
#435000
1*
#436000
b1000 .
#440000
b10001000 !
b10001000 6
b10000100 "
b10000100 5
b1001 (
b1001 1
b1000 '
b1000 0
0*
#445000
1*
#446000
b1001 .
#450000
b10001100 !
b10001100 6
b10001000 "
b10001000 5
b1010 (
b1010 1
b1001 '
b1001 0
0*
#455000
1*
#456000
b1010 .
#460000
b10010000 !
b10010000 6
b10001100 "
b10001100 5
b1011 (
b1011 1
b1010 '
b1010 0
0*
#465000
1*
#466000
b1011 .
#470000
b10010100 !
b10010100 6
b10010000 "
b10010000 5
b1100 (
b1100 1
b1011 '
b1011 0
0*
#475000
1*
#476000
b1100 .
#480000
b10011000 !
b10011000 6
b10010100 "
b10010100 5
b1101 (
b1101 1
b1100 '
b1100 0
0*
#485000
1*
#486000
b1101 .
#490000
b10011100 !
b10011100 6
b10011000 "
b10011000 5
b1110 (
b1110 1
b1101 '
b1101 0
0*
#495000
1*
#496000
b1110 .
#500000
b10100000 !
b10100000 6
b10011100 "
b10011100 5
b1111 (
b1111 1
b1110 '
b1110 0
0*
#505000
1*
#506000
b1111 .
#510000
b10100100 !
b10100100 6
b10100000 "
b10100000 5
b10000 (
b10000 1
b1111 '
b1111 0
0*
#515000
1*
#516000
b10000 .
#520000
b10101000 !
b10101000 6
b10100100 "
b10100100 5
b10001 (
b10001 1
b10000 '
b10000 0
0*
#525000
1*
#526000
b10001 .
#530000
b10101100 !
b10101100 6
b10101000 "
b10101000 5
b10010 (
b10010 1
b10001 '
b10001 0
0*
#535000
1*
#536000
b10010 .
#540000
b10110000 !
b10110000 6
b10101100 "
b10101100 5
b10011 (
b10011 1
b10010 '
b10010 0
0*
#545000
1*
#546000
b10011 .
#550000
b10110100 !
b10110100 6
b10110000 "
b10110000 5
b10100 (
b10100 1
b10011 '
b10011 0
0*
#555000
1*
#556000
b10100 .
#560000
b10111000 !
b10111000 6
b10110100 "
b10110100 5
b10101 (
b10101 1
b10100 '
b10100 0
0*
#565000
1*
#566000
b10101 .
#570000
b10111100 !
b10111100 6
b10111000 "
b10111000 5
b10110 (
b10110 1
b10101 '
b10101 0
0*
#575000
1*
#576000
b10110 .
#580000
b11000000 !
b11000000 6
b10111100 "
b10111100 5
b10111 (
b10111 1
b10110 '
b10110 0
0*
#585000
1*
#586000
b10111 .
#590000
b11000100 !
b11000100 6
b11000000 "
b11000000 5
b11000 (
b11000 1
b10111 '
b10111 0
0*
#595000
1*
#596000
b11000 .
#600000
b11001000 !
b11001000 6
b11000100 "
b11000100 5
b11001 (
b11001 1
b11000 '
b11000 0
0*
#605000
1*
#606000
b11001 .
#610000
b11001100 !
b11001100 6
b11001000 "
b11001000 5
b11010 (
b11010 1
b11001 '
b11001 0
0*
#615000
1*
#616000
b11010 .
#620000
b11010000 !
b11010000 6
b11001100 "
b11001100 5
b11011 (
b11011 1
b11010 '
b11010 0
0*
#625000
1*
#626000
b11011 .
#630000
b11010100 !
b11010100 6
b11010000 "
b11010000 5
b11100 (
b11100 1
b11011 '
b11011 0
0*
#635000
1*
#636000
b11100 .
#640000
b11011000 !
b11011000 6
b11010100 "
b11010100 5
b11101 (
b11101 1
b11100 '
b11100 0
0*
#645000
1*
#646000
b11101 .
#650000
b11011100 !
b11011100 6
b11011000 "
b11011000 5
b11110 (
b11110 1
b11101 '
b11101 0
0*
#655000
1*
#656000
b11110 .
#660000
b11100000 !
b11100000 6
b11011100 "
b11011100 5
b11111 (
b11111 1
b11110 '
b11110 0
0*
#665000
1*
#666000
b11111 .
#670000
1&
b0 %
b0 /
b11011110101011011011111011101111 )
b11011110101011011011111011101111 2
0*
#675000
1*
#680000
b0 !
b0 6
b0 "
b0 5
b0 (
b0 1
b0 '
b0 0
0&
0*
#685000
1*
#690000
1+
0*
#695000
b100000 7
1*
#700000
0*
#705000
b100000 7
1*
#710000
0*
#715000
b100000 7
b0 .
0+
1*
#720000
b1 (
b1 1
0*
#725000
1*
#726000
b1 .
#730000
b10 (
b10 1
b1 '
b1 0
0*
#735000
1*
#736000
b10 .
#740000
b11 (
b11 1
b10 '
b10 0
0*
#745000
1*
#746000
b11 .
#750000
b100 (
b100 1
b11 '
b11 0
0*
#755000
1*
#756000
b100 .
#760000
b101 (
b101 1
b100 '
b100 0
0*
#765000
1*
#766000
b101 .
#770000
b110 (
b110 1
b101 '
b101 0
0*
#775000
1*
#776000
b110 .
#780000
b111 (
b111 1
b110 '
b110 0
0*
#785000
1*
#786000
b111 .
#790000
b1000 (
b1000 1
b111 '
b111 0
0*
#795000
1*
#796000
b1000 .
#800000
b1001 (
b1001 1
b1000 '
b1000 0
0*
#805000
1*
#806000
b1001 .
#810000
b1010 (
b1010 1
b1001 '
b1001 0
0*
#815000
1*
#816000
b1010 .
#820000
b1011 (
b1011 1
b1010 '
b1010 0
0*
#825000
1*
#826000
b1011 .
#830000
b1100 (
b1100 1
b1011 '
b1011 0
0*
#835000
1*
#836000
b1100 .
#840000
b1101 (
b1101 1
b1100 '
b1100 0
0*
#845000
1*
#846000
b1101 .
#850000
b1110 (
b1110 1
b1101 '
b1101 0
0*
#855000
1*
#856000
b1110 .
#860000
b1111 (
b1111 1
b1110 '
b1110 0
0*
#865000
1*
#866000
b1111 .
#870000
b10000 (
b10000 1
b1111 '
b1111 0
0*
#875000
1*
#876000
b10000 .
#880000
b10001 (
b10001 1
b10000 '
b10000 0
0*
#885000
1*
#886000
b10001 .
#890000
b10010 (
b10010 1
b10001 '
b10001 0
0*
#895000
1*
#896000
b10010 .
#900000
b10011 (
b10011 1
b10010 '
b10010 0
0*
#905000
1*
#906000
b10011 .
#910000
b10100 (
b10100 1
b10011 '
b10011 0
0*
#915000
1*
#916000
b10100 .
#920000
b10101 (
b10101 1
b10100 '
b10100 0
0*
#925000
1*
#926000
b10101 .
#930000
b10110 (
b10110 1
b10101 '
b10101 0
0*
#935000
1*
#936000
b10110 .
#940000
b10111 (
b10111 1
b10110 '
b10110 0
0*
#945000
1*
#946000
b10111 .
#950000
b11000 (
b11000 1
b10111 '
b10111 0
0*
#955000
1*
#956000
b11000 .
#960000
b11001 (
b11001 1
b11000 '
b11000 0
0*
#965000
1*
#966000
b11001 .
#970000
b11010 (
b11010 1
b11001 '
b11001 0
0*
#975000
1*
#976000
b11010 .
#980000
b11011 (
b11011 1
b11010 '
b11010 0
0*
#985000
1*
#986000
b11011 .
#990000
b11100 (
b11100 1
b11011 '
b11011 0
0*
#995000
1*
#996000
b11100 .
#1000000
b11101 (
b11101 1
b11100 '
b11100 0
0*
#1005000
1*
#1006000
b11101 .
#1010000
b11110 (
b11110 1
b11101 '
b11101 0
0*
#1015000
1*
#1016000
b11110 .
#1020000
b11111 (
b11111 1
b11110 '
b11110 0
0*
#1025000
1*
#1026000
b11111 .
#1030000
b0 (
b0 1
b11111 '
b11111 0
0*
#1035000
1*
#1036000
b100000 .
#1040000
0*
#1045000
1*
#1050000
0*
#1055000
1*
#1060000
0*
#1065000
1*
#1070000
0*
#1075000
1*
#1080000
0*
#1085000
1*
#1090000
0*
#1095000
1*
#1100000
0*
#1105000
1*
#1110000
0*
#1115000
1*
#1120000
0*
#1125000
1*
#1130000
0*
#1135000
b1 -
1*
