Proyecto 2/src/design/RVALU.sv
module RVALU #(parameter WIDTH = 32) (
    input logic [WIDTH-1:0] a,          // Primer operando
    input logic [WIDTH-1:0] b,          // Segundo operando
    input logic [3:0] ALUCtrl,          // Control de operación
    output logic [WIDTH-1:0] ALUResult, // Resultado
    output logic Zero,                  // Flag zero
    output logic Comparison             // Resultado de comparación para branches
);

    // Señales intermedias para evitar selecciones constantes en always_comb
    logic [4:0] shift_amount;
    assign shift_amount = b[4:0];

    always_comb begin
        // Inicialización para evitar latches
        ALUResult = {WIDTH{1'b0}};
        Comparison = 1'b0;
        
        case (ALUCtrl)
            // Operaciones lógicas y aritméticas básicas
            4'b0000: ALUResult = a & b;                    // AND
            4'b0001: ALUResult = a | b;                    // OR
            4'b0010: ALUResult = $signed(a) + $signed(b);  // ADD
            4'b0011: ALUResult = (a < b) ? 32'd1 : 32'd0;  // SLTU (unsigned)
            4'b0100: ALUResult = ($signed(a) < $signed(b)) ? 32'd1 : 32'd0; // SLT (signed)
            4'b0110: ALUResult = $signed(a) - $signed(b);  // SUB
            
            // Operaciones de shift
            4'b1000: ALUResult = a << shift_amount;        // SLL (shift left logical)
            4'b1001: ALUResult = a ^ b;                    // XOR
            4'b1010: ALUResult = a >> shift_amount;        // SRL (shift right logical)
            4'b1011: ALUResult = $signed(a) >>> shift_amount; // SRA (shift right arithmetic)
            
            // Operaciones de comparación para branches (solo afectan Comparison)
            4'b1100: begin // BEQ - Branch if Equal
                Comparison = ($signed(a) == $signed(b)) ? 1'b1 : 1'b0;
                ALUResult = {WIDTH{1'b0}}; // No se usa en branches
            end
            
            4'b1101: begin // BNE - Branch if Not Equal
                Comparison = ($signed(a) != $signed(b)) ? 1'b1 : 1'b0;
                ALUResult = {WIDTH{1'b0}};
            end
            
            4'b1110: begin // BLT - Branch if Less Than (signed)
                Comparison = ($signed(a) < $signed(b)) ? 1'b1 : 1'b0;
                ALUResult = {WIDTH{1'b0}};
            end
            
            4'b1111: begin // BGE - Branch if Greater or Equal (signed)
                Comparison = ($signed(a) >= $signed(b)) ? 1'b1 : 1'b0;
                ALUResult = {WIDTH{1'b0}};
            end
            
            4'b0101: begin // BLTU - Branch if Less Than Unsigned
                Comparison = (a < b) ? 1'b1 : 1'b0;
                ALUResult = {WIDTH{1'b0}};
            end
            
            4'b0111: begin // BGEU - Branch if Greater or Equal Unsigned
                Comparison = (a >= b) ? 1'b1 : 1'b0;
                ALUResult = {WIDTH{1'b0}};
            end
            
            default: begin
                ALUResult = $signed(a) + $signed(b); // Default: ADD
                Comparison = 1'b0;
            end
        endcase
        
        // Zero flag - para operaciones que requieran igualdad o desigualdad en operaciones
        Zero = (ALUResult ==0)?1:0;
    end
endmodule

Proyecto_2/src/sim/RVALU_tb.sv
`timescale 1ns / 1ps

module RVALU_tb#(parameter WIDTH=32);
    // Señales del testbench
    logic [WIDTH-1:0] a;
    logic [WIDTH-1:0] b;
    logic [3:0] ALUCtrl;
    logic [WIDTH-1:0] ALUResult;
    logic Zero;
    logic Comparison;
    
    // Variables para verificación
    logic [WIDTH-1:0] expected_result;
    logic expected_zero;
    logic expected_comparison;
    integer test_count = 0;
    integer pass_count = 0;
    integer fail_count = 0;
    
    // Instanciación del DUT (Device Under Test)
    RVALU #(.WIDTH(WIDTH)) dut (
        .a(a),
        .b(b),
        .ALUCtrl(ALUCtrl),
        .ALUResult(ALUResult),
        .Zero(Zero),
        .Comparison(Comparison)
    );
    
    // Función para verificar resultados
    task check_result(
        input [WIDTH-1:0] exp_result,
        input exp_zero,
        input exp_comparison,
        input string operation_name
    );
        test_count++;
        if (ALUResult === exp_result && Zero === exp_zero && Comparison === exp_comparison) begin
            $display("✓ PASS: %s - a=%h, b=%h, ALUCtrl=%b", operation_name, a, b, ALUCtrl);
            $display("    Result: %h, Zero: %b, Comparison: %b", ALUResult, Zero, Comparison);
            pass_count++;
        end else begin
            $display("✗ FAIL: %s - a=%h, b=%h, ALUCtrl=%b", operation_name, a, b, ALUCtrl);
            $display("    Expected: Result=%h, Zero=%b, Comparison=%b", exp_result, exp_zero, exp_comparison);
            $display("    Got:      Result=%h, Zero=%b, Comparison=%b", ALUResult, Zero, Comparison);
            fail_count++;
        end
        $display("");
    endtask
    
    // Función para calcular resultado esperado
    task calculate_expected(
        input [WIDTH-1:0] op_a,
        input [WIDTH-1:0] op_b,
        input [3:0] ctrl,
        output [WIDTH-1:0] exp_result,
        output exp_zero,
        output exp_comparison
    );
        exp_comparison = 1'b0; // Default
        
        case (ctrl)
            4'b0000: exp_result = op_a & op_b;                        // AND
            4'b0001: exp_result = op_a | op_b;                        // OR
            4'b0010: exp_result = $signed(op_a) + $signed(op_b);      // ADD
            4'b0011: exp_result = (op_a < op_b) ? 32'd1 : 32'd0;      // SLTU
            4'b0100: exp_result = ($signed(op_a) < $signed(op_b)) ? 32'd1 : 32'd0; // SLT
            4'b0110: exp_result = $signed(op_a) - $signed(op_b);      // SUB
            4'b1000: exp_result = op_a << op_b[4:0];                  // SLL
            4'b1001: exp_result = op_a ^ op_b;                        // XOR
            4'b1010: exp_result = op_a >> op_b[4:0];                  // SRL
            4'b1011: exp_result = $signed(op_a) >>> op_b[4:0];        // SRA
            
            // Branch operations
            4'b1100: begin // BEQ
                exp_result = {WIDTH{1'b0}};
                exp_comparison = ($signed(op_a) == $signed(op_b)) ? 1'b1 : 1'b0;
            end
            4'b1101: begin // BNE
                exp_result = {WIDTH{1'b0}};
                exp_comparison = ($signed(op_a) != $signed(op_b)) ? 1'b1 : 1'b0;
            end
            4'b1110: begin // BLT
                exp_result = {WIDTH{1'b0}};
                exp_comparison = ($signed(op_a) < $signed(op_b)) ? 1'b1 : 1'b0;
            end
            4'b1111: begin // BGE
                exp_result = {WIDTH{1'b0}};
                exp_comparison = ($signed(op_a) >= $signed(op_b)) ? 1'b1 : 1'b0;
            end
            4'b0101: begin // BLTU
                exp_result = {WIDTH{1'b0}};
                exp_comparison = (op_a < op_b) ? 1'b1 : 1'b0;
            end
            4'b0111: begin // BGEU
                exp_result = {WIDTH{1'b0}};
                exp_comparison = (op_a >= op_b) ? 1'b1 : 1'b0;
            end
            default: exp_result = $signed(op_a) + $signed(op_b);      // Default ADD
        endcase
        
        exp_zero = (exp_result == 0) ? 1'b1 : 1'b0;
    endtask
    
    // Test de una operación específica
    task test_operation(
        input [WIDTH-1:0] test_a,
        input [WIDTH-1:0] test_b,
        input [3:0] test_ctrl,
        input string op_name
    );
        a = test_a;
        b = test_b;
        ALUCtrl = test_ctrl;
        #1; // Pequeño delay para combinational logic
        
        calculate_expected(test_a, test_b, test_ctrl, expected_result, expected_zero, expected_comparison);
        check_result(expected_result, expected_zero, expected_comparison, op_name);
    endtask
    
    // Proceso principal de testing
    initial begin
        $display("=== Iniciando testbench para RVALU ===");
        $display("Ancho de datos: %d bits", WIDTH);
        $display("==========================================\n");
        
        // Test 1: Operaciones lógicas básicas
        $display("--- Test 1: Operaciones Lógicas ---");
        test_operation(32'hAAAA5555, 32'h5555AAAA, 4'b0000, "AND");
        test_operation(32'hAAAA5555, 32'h5555AAAA, 4'b0001, "OR");
        test_operation(32'h12345678, 32'h87654321, 4'b1001, "XOR");
        
        // Test 2: Operaciones aritméticas
        $display("--- Test 2: Operaciones Aritméticas ---");
        test_operation(32'd100, 32'd50, 4'b0010, "ADD positivos");
        test_operation(32'd100, 32'd150, 4'b0110, "SUB (100-150)");
        test_operation(-32'd50, 32'd25, 4'b0010, "ADD con negativo");
        test_operation(32'd0, 32'd0, 4'b0010, "ADD ceros (test Zero flag)");
        
        // Test 3: Operaciones de comparación (SLT/SLTU)
        $display("--- Test 3: Comparaciones SLT/SLTU ---");
        test_operation(32'd10, 32'd20, 4'b0100, "SLT (10 < 20)");
        test_operation(32'd20, 32'd10, 4'b0100, "SLT (20 < 10)");
        test_operation(-32'd10, 32'd5, 4'b0100, "SLT signed (-10 < 5)");
        test_operation(32'hFFFFFFFF, 32'd1, 4'b0011, "SLTU unsigned (0xFFFFFFFF < 1)");
        test_operation(32'hFFFFFFFF, 32'd1, 4'b0100, "SLT signed (0xFFFFFFFF < 1)");
        
        // Test 4: Operaciones de shift
        $display("--- Test 4: Operaciones de Shift ---");
        test_operation(32'h12345678, 32'd4, 4'b1000, "SLL shift left 4");
        test_operation(32'h12345678, 32'd4, 4'b1010, "SRL shift right 4");
        test_operation(32'h80000000, 32'd4, 4'b1011, "SRA arithmetic shift right 4");
        test_operation(32'h12345678, 32'd0, 4'b1000, "SLL shift 0");
        
        // Test 5: Operaciones de branch
        $display("--- Test 5: Operaciones de Branch ---");
        test_operation(32'd100, 32'd100, 4'b1100, "BEQ iguales");
        test_operation(32'd100, 32'd50, 4'b1100, "BEQ diferentes");
        test_operation(32'd100, 32'd50, 4'b1101, "BNE diferentes");
        test_operation(32'd100, 32'd100, 4'b1101, "BNE iguales");
        test_operation(32'd50, 32'd100, 4'b1110, "BLT (50 < 100)");
        test_operation(32'd100, 32'd50, 4'b1110, "BLT (100 < 50)");
        test_operation(32'd100, 32'd50, 4'b1111, "BGE (100 >= 50)");
        test_operation(32'd50, 32'd100, 4'b1111, "BGE (50 >= 100)");
        
        // Test 6: Branch unsigned
        $display("--- Test 6: Branch Unsigned ---");
        test_operation(32'hFFFFFFFF, 32'd1, 4'b0101, "BLTU unsigned (0xFFFFFFFF < 1)");
        test_operation(32'd1, 32'hFFFFFFFF, 4'b0101, "BLTU unsigned (1 < 0xFFFFFFFF)");
        test_operation(32'hFFFFFFFF, 32'd1, 4'b0111, "BGEU unsigned (0xFFFFFFFF >= 1)");
        test_operation(32'd1, 32'hFFFFFFFF, 4'b0111, "BGEU unsigned (1 >= 0xFFFFFFFF)");
        
        // Test 7: Casos edge y valores extremos
        $display("--- Test 7: Casos Extremos ---");
        test_operation(32'hFFFFFFFF, 32'd1, 4'b0010, "ADD overflow");
        test_operation(32'h80000000, 32'd1, 4'b0110, "SUB underflow");
        test_operation(32'hFFFFFFFF, 32'd31, 4'b1000, "SLL máximo shift");
        test_operation(32'hFFFFFFFF, 32'd31, 4'b1010, "SRL máximo shift");
        test_operation(32'h80000000, 32'd31, 4'b1011, "SRA máximo shift");
        
        // Test 8: Operación default
        $display("--- Test 8: Operación Default ---");
        test_operation(32'd10, 32'd20, 4'b0001, "OR operation"); // Test normal

        
        // Test 9: Test del flag Zero
        $display("--- Test 9: Verificación Flag Zero ---");
        test_operation(32'd0, 32'd0, 4'b0000, "AND que resulta en 0");
        test_operation(32'hFFFF0000, 32'h0000FFFF, 4'b0000, "AND que resulta en 0");
        test_operation(32'd50, 32'd50, 4'b0110, "SUB que resulta en 0");
        
        // Resumen final
        $display("\n==========================================");
        $display("=== RESUMEN DE RESULTADOS ===");
        $display("Total de tests: %d", test_count);
        $display("Tests exitosos: %d", pass_count);
        $display("Tests fallidos: %d", fail_count);
        $display("Porcentaje de éxito: %.2f%%", (real'(pass_count) / real'(test_count)) * 100.0);
        
        if (fail_count == 0) begin
            $display(" ¡TODOS LOS TESTS PASARON! 🎉");
        end else begin
            $display("  Algunos tests fallaron. Revisar implementación.");
        end
        
        $display("==========================================");
        $finish;
    end

        // Sistema de guardado de los resultados del testbench.
    initial begin
        $dumpfile("RVALU_tb.vcd");
        $dumpvars(0, RVALU_tb);
    end 

endmodule

Proyecto_3/src/build/RVALU_tb.vcd
$date
	Sun Jun 08 15:59:41 2025
$end
$version
	Icarus Verilog
$end
$timescale
	1ps
$end
$scope module RVALU_tb $end
$var wire 1 ! Zero $end
$var wire 1 " Comparison $end
$var wire 32 # ALUResult [31:0] $end
$var parameter 32 $ WIDTH $end
$var reg 4 % ALUCtrl [3:0] $end
$var reg 32 & a [31:0] $end
$var reg 32 ' b [31:0] $end
$var reg 1 ( expected_comparison $end
$var reg 32 ) expected_result [31:0] $end
$var reg 1 * expected_zero $end
$var integer 32 + fail_count [31:0] $end
$var integer 32 , pass_count [31:0] $end
$var integer 32 - test_count [31:0] $end
$scope module dut $end
$var wire 4 . ALUCtrl [3:0] $end
$var wire 32 / a [31:0] $end
$var wire 32 0 b [31:0] $end
$var wire 5 1 shift_amount [4:0] $end
$var parameter 32 2 WIDTH $end
$var reg 32 3 ALUResult [31:0] $end
$var reg 1 " Comparison $end
$var reg 1 ! Zero $end
$upscope $end
$scope task calculate_expected $end
$var reg 4 4 ctrl [3:0] $end
$var reg 1 5 exp_comparison $end
$var reg 32 6 exp_result [31:0] $end
$var reg 1 7 exp_zero $end
$var reg 32 8 op_a [31:0] $end
$var reg 32 9 op_b [31:0] $end
$upscope $end
$scope task check_result $end
$var reg 1 : exp_comparison $end
$var reg 32 ; exp_result [31:0] $end
$var reg 1 < exp_zero $end
$upscope $end
$scope task test_operation $end
$var reg 32 = test_a [31:0] $end
$var reg 32 > test_b [31:0] $end
$var reg 4 ? test_ctrl [3:0] $end
$upscope $end
$upscope $end
$enddefinitions $end
$comment Show the parameter values. $end
$dumpall
b100000 2
b100000 $
$end
#0
$dumpvars
b0 ?
b1010101010101011010101010101010 >
b10101010101010100101010101010101 =
x<
bx ;
x:
bx 9
bx 8
x7
bx 6
x5
bx 4
b0 3
b1010 1
b1010101010101011010101010101010 0
b10101010101010100101010101010101 /
b0 .
b0 -
b0 ,
b0 +
x*
bx )
x(
b1010101010101011010101010101010 '
b10101010101010100101010101010101 &
b0 %
b0 #
0"
1!
$end
#1000
0!
b11111111111111111111111111111111 #
b11111111111111111111111111111111 3
b1 %
b1 .
b1 ?
b1 ,
b1 -
0:
1<
b0 ;
0(
1*
b0 )
17
b0 6
05
b0 4
b1010101010101011010101010101010 9
b10101010101010100101010101010101 8
#2000
b1 1
b10010101010100010001010101011001 #
b10010101010100010001010101011001 3
b1001 %
b1001 .
b10000111011001010100001100100001 '
b10000111011001010100001100100001 0
b10010001101000101011001111000 &
b10010001101000101011001111000 /
b1001 ?
b10000111011001010100001100100001 >
b10010001101000101011001111000 =
b10 ,
b10 -
0<
b11111111111111111111111111111111 ;
0*
b11111111111111111111111111111111 )
07
b11111111111111111111111111111111 6
b1 4
#3000
b10010 1
b10010110 #
b10010110 3
b10 %
b10 .
b110010 '
b110010 0
b1100100 &
b1100100 /
b10 ?
b110010 >
b1100100 =
b11 ,
b11 -
b10010101010100010001010101011001 ;
b10010101010100010001010101011001 )
b10010101010100010001010101011001 6
b1001 4
b10000111011001010100001100100001 9
b10010001101000101011001111000 8
#4000
b11111111111111111111111111001110 #
b11111111111111111111111111001110 3
b10110 1
b110 %
b110 .
b10010110 '
b10010110 0
b110 ?
b10010110 >
b100 ,
b100 -
b10010110 ;
b10010110 )
b10010110 6
b10 4
b110010 9
b1100100 8
#5000
b11001 1
b11111111111111111111111111100111 #
b11111111111111111111111111100111 3
b10 %
b10 .
b11001 '
b11001 0
b11111111111111111111111111001110 &
b11111111111111111111111111001110 /
b10 ?
b11001 >
b11111111111111111111111111001110 =
b101 ,
b101 -
b11111111111111111111111111001110 ;
b11111111111111111111111111001110 )
b11111111111111111111111111001110 6
b110 4
b10010110 9
#6000
b0 1
1!
b0 #
b0 3
b0 '
b0 0
b0 &
b0 /
b0 >
b0 =
b110 ,
b110 -
b11111111111111111111111111100111 ;
b11111111111111111111111111100111 )
b11111111111111111111111111100111 6
b10 4
b11001 9
b11111111111111111111111111001110 8
#7000
b10100 1
0!
b1 #
b1 3
b100 %
b100 .
b10100 '
b10100 0
b1010 &
b1010 /
b100 ?
b10100 >
b1010 =
b111 ,
b111 -
1<
b0 ;
1*
b0 )
17
b0 6
b0 9
b0 8
#8000
b1010 1
1!
b0 #
b0 3
b1010 '
b1010 0
b10100 &
b10100 /
b1010 >
b10100 =
b1000 ,
b1000 -
0<
b1 ;
0*
b1 )
07
b1 6
b100 4
b10100 9
b1010 8
#9000
b101 1
0!
b1 #
b1 3
b101 '
b101 0
b11111111111111111111111111110110 &
b11111111111111111111111111110110 /
b101 >
b11111111111111111111111111110110 =
b1001 ,
b1001 -
1<
b0 ;
1*
b0 )
17
b0 6
b1010 9
b10100 8
#10000
b1 1
1!
b0 #
b0 3
b11 %
b11 .
b1 '
b1 0
b11111111111111111111111111111111 &
b11111111111111111111111111111111 /
b11 ?
b1 >
b11111111111111111111111111111111 =
b1010 ,
b1010 -
0<
b1 ;
0*
b1 )
07
b1 6
b101 9
b11111111111111111111111111110110 8
#11000
0!
b1 #
b1 3
b100 %
b100 .
b100 ?
b1011 ,
b1011 -
1<
b0 ;
1*
b0 )
17
b0 6
b11 4
b1 9
b11111111111111111111111111111111 8
#12000
b100 1
b100011010001010110011110000000 #
b100011010001010110011110000000 3
b1000 %
b1000 .
b100 '
b100 0
b10010001101000101011001111000 &
b10010001101000101011001111000 /
b1000 ?
b100 >
b10010001101000101011001111000 =
b1100 ,
b1100 -
0<
b1 ;
0*
b1 )
07
b1 6
b100 4
#13000
b1001000110100010101100111 #
b1001000110100010101100111 3
b1010 %
b1010 .
b1010 ?
b1101 ,
b1101 -
b100011010001010110011110000000 ;
b100011010001010110011110000000 )
b100011010001010110011110000000 6
b1000 4
b100 9
b10010001101000101011001111000 8
#14000
b11111000000000000000000000000000 #
b11111000000000000000000000000000 3
b1011 %
b1011 .
b10000000000000000000000000000000 &
b10000000000000000000000000000000 /
b1011 ?
b10000000000000000000000000000000 =
b1110 ,
b1110 -
b1001000110100010101100111 ;
b1001000110100010101100111 )
b1001000110100010101100111 6
b1010 4
#15000
b0 1
b10010001101000101011001111000 #
b10010001101000101011001111000 3
b1000 %
b1000 .
b0 '
b0 0
b10010001101000101011001111000 &
b10010001101000101011001111000 /
b1000 ?
b0 >
b10010001101000101011001111000 =
b1111 ,
b1111 -
b11111000000000000000000000000000 ;
b11111000000000000000000000000000 )
b11111000000000000000000000000000 6
b1011 4
b10000000000000000000000000000000 8
#16000
b100 1
1!
1"
b0 #
b0 3
b1100 %
b1100 .
b1100100 '
b1100100 0
b1100100 &
b1100100 /
b1100 ?
b1100100 >
b1100100 =
b10000 ,
b10000 -
b10010001101000101011001111000 ;
b10010001101000101011001111000 )
b10010001101000101011001111000 6
b1000 4
b0 9
b10010001101000101011001111000 8
#17000
0"
b10010 1
b110010 '
b110010 0
b110010 >
b10001 ,
b10001 -
1:
1<
b0 ;
1(
1*
b0 )
17
15
b0 6
b1100 4
b1100100 9
b1100100 8
#18000
1"
b1101 %
b1101 .
b1101 ?
b10010 ,
b10010 -
0:
0(
05
b110010 9
#19000
0"
b100 1
b1100100 '
b1100100 0
b1100100 >
b10011 ,
b10011 -
1:
1(
15
b1101 4
#20000
1"
b1110 %
b1110 .
b110010 &
b110010 /
b1110 ?
b110010 =
b10100 ,
b10100 -
0:
0(
05
b1100100 9
#21000
b10010 1
0"
b110010 '
b110010 0
b1100100 &
b1100100 /
b110010 >
b1100100 =
b10101 ,
b10101 -
1:
1(
15
b1110 4
b110010 8
#22000
1"
b1111 %
b1111 .
b1111 ?
b10110 ,
b10110 -
0:
0(
05
b110010 9
b1100100 8
#23000
b100 1
0"
b1100100 '
b1100100 0
b110010 &
b110010 /
b1100100 >
b110010 =
b10111 ,
b10111 -
1:
1(
15
b1111 4
#24000
b1 1
b101 %
b101 .
b1 '
b1 0
b11111111111111111111111111111111 &
b11111111111111111111111111111111 /
b101 ?
b1 >
b11111111111111111111111111111111 =
b11000 ,
b11000 -
0:
0(
05
b1100100 9
b110010 8
#25000
b11111 1
1"
b11111111111111111111111111111111 '
b11111111111111111111111111111111 0
b1 &
b1 /
b11111111111111111111111111111111 >
b1 =
b11001 ,
b11001 -
b101 4
b1 9
b11111111111111111111111111111111 8
#26000
b1 1
1"
b111 %
b111 .
b1 '
b1 0
b11111111111111111111111111111111 &
b11111111111111111111111111111111 /
b111 ?
b1 >
b11111111111111111111111111111111 =
b11010 ,
b11010 -
1:
1(
15
b11111111111111111111111111111111 9
b1 8
#27000
b11111 1
0"
b11111111111111111111111111111111 '
b11111111111111111111111111111111 0
b1 &
b1 /
b11111111111111111111111111111111 >
b1 =
b11011 ,
b11011 -
15
b111 4
b1 9
b11111111111111111111111111111111 8
#28000
b1 1
b10 %
b10 .
b1 '
b1 0
b11111111111111111111111111111111 &
b11111111111111111111111111111111 /
b10 ?
b1 >
b11111111111111111111111111111111 =
b11100 ,
b11100 -
0:
0(
05
b11111111111111111111111111111111 9
b1 8
#29000
0!
b1111111111111111111111111111111 #
b1111111111111111111111111111111 3
b110 %
b110 .
b10000000000000000000000000000000 &
b10000000000000000000000000000000 /
b110 ?
b10000000000000000000000000000000 =
b11101 ,
b11101 -
b10 4
b1 9
b11111111111111111111111111111111 8
#30000
b11111 1
b10000000000000000000000000000000 #
b10000000000000000000000000000000 3
b1000 %
b1000 .
b11111 '
b11111 0
b11111111111111111111111111111111 &
b11111111111111111111111111111111 /
b1000 ?
b11111 >
b11111111111111111111111111111111 =
b11110 ,
b11110 -
0<
b1111111111111111111111111111111 ;
0*
b1111111111111111111111111111111 )
07
b1111111111111111111111111111111 6
b110 4
b10000000000000000000000000000000 8
#31000
b1 #
b1 3
b1010 %
b1010 .
b1010 ?
b11111 ,
b11111 -
b10000000000000000000000000000000 ;
b10000000000000000000000000000000 )
b10000000000000000000000000000000 6
b1000 4
b11111 9
b11111111111111111111111111111111 8
#32000
b11111111111111111111111111111111 #
b11111111111111111111111111111111 3
b1011 %
b1011 .
b10000000000000000000000000000000 &
b10000000000000000000000000000000 /
b1011 ?
b10000000000000000000000000000000 =
b100000 ,
b100000 -
b1 ;
b1 )
b1 6
b1010 4
#33000
b10100 1
b11110 #
b11110 3
b1 %
b1 .
b10100 '
b10100 0
b1010 &
b1010 /
b1 ?
b10100 >
b1010 =
b100001 ,
b100001 -
b11111111111111111111111111111111 ;
b11111111111111111111111111111111 )
b11111111111111111111111111111111 6
b1011 4
b10000000000000000000000000000000 8
#34000
b0 1
1!
b0 #
b0 3
b0 %
b0 .
b0 '
b0 0
b0 &
b0 /
b0 ?
b0 >
b0 =
b100010 ,
b100010 -
b11110 ;
b11110 )
b11110 6
b1 4
b10100 9
b1010 8
#35000
b11111 1
b1111111111111111 '
b1111111111111111 0
b11111111111111110000000000000000 &
b11111111111111110000000000000000 /
b1111111111111111 >
b11111111111111110000000000000000 =
b100011 ,
b100011 -
1<
b0 ;
1*
b0 )
17
b0 6
b0 4
b0 9
b0 8
#36000
b10010 1
b110 %
b110 .
b110010 '
b110010 0
b110010 &
b110010 /
b110 ?
b110010 >
b110010 =
b100100 ,
b100100 -
b1111111111111111 9
b11111111111111110000000000000000 8
#37000
b100101 ,
b100101 -
b110 4
b110010 9
b110010 8
